Workbook
Name UPDATE: 'Data Sheet'!$E$1

Sheet Financials

Sheet Historical FS
B2: ="HISTORICAL FINANCIAL STATEMENT -" &'Data Sheet'!B1 -> HISTORICAL FINANCIAL STATEMENT -TATA MOTORS LTD
B3: YEARS | C3: ='Data Sheet'!B16 -> 42460 | D3: ='Data Sheet'!C16 -> 42825 | E3: ='Data Sheet'!D16 -> 43190 | F3: ='Data Sheet'!E16 -> 43555 | G3: ='Data Sheet'!F16 -> 43921 | H3: ='Data Sheet'!G16 -> 44286 | I3: ='Data Sheet'!H16 -> 44651 | J3: ='Data Sheet'!I16 -> 45016 | ... L3: ='Data Sheet'!K16 -> 45747 | M3: LTM
A5: # | B5: INCOME STATEMENT
B6: Sales | C6: =IFERROR('Data Sheet'!B17,0) -> 273045.6 | D6: =IFERROR('Data Sheet'!C17,0) -> 269692.51 | E6: =IFERROR('Data Sheet'!D17,0) -> 291550.48 | F6: =IFERROR('Data Sheet'!E17,0) -> 301938.4 | G6: =IFERROR('Data Sheet'!F17,0) -> 261067.97 | H6: =IFERROR('Data Sheet'!G17,0) -> 249794.75 | I6: =IFERROR('Data Sheet'!H17,0) -> 278453.62 | J6: =IFERROR('Data Sheet'!I17,0) -> 345966.97 | ... L6: =IFERROR('Data Sheet'!K17,0) -> 439695 | M6: =IFERROR(SUM('Data Sheet'!H17:K17),0) -> 1498131.6
B7: Sales Growth | C7: - | D7: =D6/C6-1 -> -0.01228033 | E7: =E6/D6-1 -> 0.081047746 | F7: =F6/E6-1 -> 0.035629919 | G7: =G6/F6-1 -> -0.13536016 | H7: =H6/G6-1 -> -0.043181168 | I7: =I6/H6-1 -> 0.11472967 | J7: =J6/I6-1 -> 0.24245815 | K7: =K6/J6-1 -> 0.25450126 | ... M7: =M6/L6-1 -> 2.4072063
B9: COGS | C9: =IFERROR(SUM('Data Sheet'!B18,'Data Sheet'!B20,'Data Sheet'!B21,'Data Sheet'!B22)-1*'Data Sheet'!B19,0) -> 205509.07 | D9: =IFERROR(SUM('Data Sheet'!C18,'Data Sheet'!C20,'Data Sheet'!C21,'Data Sheet'!C22)-1*'Data Sheet'!C19,0) -> 205454.24 | E9: =IFERROR(SUM('Data Sheet'!D18,'Data Sheet'!D20,'Data Sheet'!D21,'Data Sheet'!D22)-1*'Data Sheet'!D19,0) -> 228429.83 | F9: =IFERROR(SUM('Data Sheet'!E18,'Data Sheet'!E20,'Data Sheet'!E21,'Data Sheet'!E22)-1*'Data Sheet'!E19,0) -> 242845.53 | G9: =IFERROR(SUM('Data Sheet'!F18,'Data Sheet'!F20,'Data Sheet'!F21,'Data Sheet'!F22)-1*'Data Sheet'!F19,0) -> 210376.07 | H9: =IFERROR(SUM('Data Sheet'!G18,'Data Sheet'!G20,'Data Sheet'!G21,'Data Sheet'!G22)-1*'Data Sheet'!G19,0) -> 195326.04 | I9: =IFERROR(SUM('Data Sheet'!H18,'Data Sheet'!H20,'Data Sheet'!H21,'Data Sheet'!H22)-1*'Data Sheet'!H19,0) -> 223300.01 | J9: =IFERROR(SUM('Data Sheet'!I18,'Data Sheet'!I20,'Data Sheet'!I21,'Data Sheet'!I22)-1*'Data Sheet'!I19,0) -> 274403.64 | ... L9: =IFERROR(SUM('Data Sheet'!K18,'Data Sheet'!K20,'Data Sheet'!K21,'Data Sheet'!K22)-1*'Data Sheet'!K19,0) -> 340809 | M9: =IFERROR(SUM('Data Sheet'!H43:K43),0) -> 384424
B10: COGS % Sales | C10: =C9/C6 -> 0.75265476 | D10: =D9/D6 -> 0.76180922 | E10: =E9/E6 -> 0.7835001 | F10: =F9/F6 -> 0.80428833 | G10: =G9/G6 -> 0.80582873 | H10: =H9/H6 -> 0.78194614 | I10: =I9/I6 -> 0.80192892 | J10: =J9/J6 -> 0.79314982 | ... L10: =L9/L6 -> 0.7751032 | M10: -
B12: GROSS PROFIT | C12: =C6-C9 -> 67536.53 | D12: =D6-D9 -> 64238.27 | E12: =E6-E9 -> 63120.65 | F12: =F6-F9 -> 59092.87 | G12: =G6-G9 -> 50691.9 | H12: =H6-H9 -> 54468.71 | I12: =I6-I9 -> 55153.61 | J12: =J6-J9 -> 71563.33 | ... M12: =M6-M9 -> 1113707.6
B13: Gross Margins | C13: =C12/C6 -> 0.24734524 | D13: =D12/D6 -> 0.23819078 | E13: =E12/E6 -> 0.2164999 | F13: =F12/F6 -> 0.19571167 | G13: =G12/G6 -> 0.19417127 | H13: =H12/H6 -> 0.21805386 | I13: =I12/I6 -> 0.19807108 | J13: =J12/J6 -> 0.20685018 | ... M13: =M12/M6 -> 0.74339771
B15: SELLING AND GENERAL EXPENSES | C15: =IFERROR(SUM('Data Sheet'!B23,'Data Sheet'!B24),0) -> 29141.28 | D15: =IFERROR(SUM('Data Sheet'!C23,'Data Sheet'!C24),0) -> 34649.58 | E15: =IFERROR(SUM('Data Sheet'!D23,'Data Sheet'!D24),0) -> 31662.97 | F15: =IFERROR(SUM('Data Sheet'!E23,'Data Sheet'!E24),0) -> 34428.54 | G15: =IFERROR(SUM('Data Sheet'!F23,'Data Sheet'!F24),0) -> 32704.83 | H15: =IFERROR(SUM('Data Sheet'!G23,'Data Sheet'!G24),0) -> 22181.28 | I15: =IFERROR(SUM('Data Sheet'!H23,'Data Sheet'!H24),0) -> 30433.52 | J15: =IFERROR(SUM('Data Sheet'!I23,'Data Sheet'!I24),0) -> 39747.53 | ... L15: =IFERROR(SUM('Data Sheet'!K23,'Data Sheet'!K24),0) -> 43670
B16: S&G Exp % Sales | C16: =C15/C6 -> 0.10672679 | D16: =D15/D6 -> 0.1284781 | E16: =E15/E6 -> 0.10860202 | F16: =F15/F6 -> 0.11402505 | G16: =G15/G6 -> 0.12527324 | H16: =H15/H6 -> 0.088798023 | I16: =I15/I6 -> 0.10929475 | J16: =J15/J6 -> 0.11488822 | ... M16: =M15/M6 -> 0
B18: EBITDA | C18: =C12-C15 -> 38395.25 | D18: =D12-D15 -> 29588.69 | E18: =E12-E15 -> 31457.68 | F18: =F12-F15 -> 24664.33 | G18: =G12-G15 -> 17987.07 | H18: =H12-H15 -> 32287.43 | I18: =I12-I15 -> 24720.09 | J18: =J12-J15 -> 31815.8 | ... M18: =M12-M15 -> 1113707.6
B19: EBITDA Margins | C19: =C18/C6 -> 0.14061845 | D19: =D18/D6 -> 0.10971269 | E19: =E18/E6 -> 0.10789788 | F19: =F18/F6 -> 0.081686629 | G19: =G18/G6 -> 0.068898034 | H19: =H18/H6 -> 0.12925584 | I19: =I18/I6 -> 0.088776328 | J19: =J18/J6 -> 0.091961958 | ... M19: =M18/M6 -> 0.74339771
B21: Interest | C21: =IFERROR('Data Sheet'!B27,0) -> 4889.08 | D21: =IFERROR('Data Sheet'!C27,0) -> 4238.01 | E21: =IFERROR('Data Sheet'!D27,0) -> 4681.79 | F21: =IFERROR('Data Sheet'!E27,0) -> 5758.6 | G21: =IFERROR('Data Sheet'!F27,0) -> 7243.33 | H21: =IFERROR('Data Sheet'!G27,0) -> 8097.17 | I21: =IFERROR('Data Sheet'!H27,0) -> 9311.86 | J21: =IFERROR('Data Sheet'!I27,0) -> 10225.48 | ... L21: =IFERROR('Data Sheet'!K27,0) -> 5083 | M21: =IFERROR(SUM('Data Sheet'!H46:K46),0) -> 6317
B22: Interest % Sales | C22: =C21/C6 -> 0.017905727 | D22: =D21/D6 -> 0.01571423 | E22: =E21/E6 -> 0.016058248 | F22: =F21/F6 -> 0.019072102 | G22: =G21/G6 -> 0.027744997 | H22: =H21/H6 -> 0.032415293 | I22: =I21/I6 -> 0.033441332 | J22: =J21/J6 -> 0.029556232 | ... M22: =M21/M6 -> 0.0042165855
B24: Depreciation | C24: =IFERROR('Data Sheet'!B26,0) -> 16710.78 | D24: =IFERROR('Data Sheet'!C26,0) -> 17904.99 | E24: =IFERROR('Data Sheet'!D26,0) -> 21553.59 | F24: =IFERROR('Data Sheet'!E26,0) -> 23590.63 | G24: =IFERROR('Data Sheet'!F26,0) -> 21425.43 | H24: =IFERROR('Data Sheet'!G26,0) -> 23546.71 | I24: =IFERROR('Data Sheet'!H26,0) -> 24835.69 | J24: =IFERROR('Data Sheet'!I26,0) -> 24860.36 | ... L24: =IFERROR('Data Sheet'!K26,0) -> 23256 | M24: =IFERROR(SUM('Data Sheet'!H45:K45),0) -> 23273
B25: Depreciation % Sales | C25: =C24/C6 -> 0.061201426 | D25: =D24/D6 -> 0.066390387 | E25: =E24/E6 -> 0.073927472 | F25: =F24/F6 -> 0.078130605 | G25: =G24/G6 -> 0.082068398 | H25: =H24/H6 -> 0.094264231 | I25: =I24/I6 -> 0.089191478 | J25: =J24/J6 -> 0.071857611 | ... M25: =M24/M6 -> 0.015534683
B27: Earnings Before Tax | C27: =IFERROR(C18-SUM(C21,C24),0) -> 16795.39 | D27: =IFERROR(D18-SUM(D21,D24),0) -> 7445.69 | E27: =IFERROR(E18-SUM(E21,E24),0) -> 5222.3 | F27: =IFERROR(F18-SUM(F21,F24),0) -> -4684.9 | G27: =IFERROR(G18-SUM(G21,G24),0) -> -10681.69 | H27: =IFERROR(H18-SUM(H21,H24),0) -> 643.55 | I27: =IFERROR(I18-SUM(I21,I24),0) -> -9427.46 | J27: =IFERROR(J18-SUM(J21,J24),0) -> -3270.04 | ... M27: =IFERROR(M18-SUM(M21,M24),0) -> 1084117.6
B28: EBT % Sales | C28: =C27/C6 -> 0.061511301 | D28: =D27/D6 -> 0.027608071 | E28: =E27/E6 -> 0.017912164 | F28: =F27/F6 -> -0.015516079 | G28: =G27/G6 -> -0.04091536 | H28: =H27/H6 -> 0.0025763152 | I28: =I27/I6 -> -0.033856482 | J28: =J27/J6 -> -0.009451885 | ... M28: =M27/M6 -> 0.72364644
B30: Tax | C30: =IFERROR('Data Sheet'!B29,0) -> 3025.05 | D30: =IFERROR('Data Sheet'!C29,0) -> 3251.23 | E30: =IFERROR('Data Sheet'!D29,0) -> 4341.93 | F30: =IFERROR('Data Sheet'!E29,0) -> -2437.45 | G30: =IFERROR('Data Sheet'!F29,0) -> 395.25 | H30: =IFERROR('Data Sheet'!G29,0) -> 2541.86 | I30: =IFERROR('Data Sheet'!H29,0) -> 4231.29 | J30: =IFERROR('Data Sheet'!I29,0) -> 704.06 | ... L30: =IFERROR('Data Sheet'!K29,0) -> 10502 | M30: =IFERROR(SUM('Data Sheet'!H48:K48),0) -> 10563
B31: Effective Tax Rate | C31: =C30/C27 -> 0.18011192 | D31: =D30/D27 -> 0.43665933 | E31: =E30/E27 -> 0.83142102 | F31: =F30/F27 -> 0.52027791 | G31: =G30/G27 -> -0.037002572 | H31: =H30/H27 -> 3.9497475 | I31: =I30/I27 -> -0.44882609 | J31: =J30/J27 -> -0.21530623 | ... M31: =M30/M27 -> 0.009743408
B33: Net Profit | C33: =C27-C30 -> 13770.34 | D33: =D27-D30 -> 4194.46 | E33: =E27-E30 -> 880.37 | F33: =F27-F30 -> -2247.45 | G33: =G27-G30 -> -11076.94 | H33: =H27-H30 -> -1898.31 | I33: =I27-I30 -> -13658.75 | J33: =J27-J30 -> -3974.1 | ... M33: =M27-M30 -> 1073554.6
B34: Net Margin | C34: =C33/C6 -> 0.050432382 | D34: =D33/D6 -> 0.015552749 | E34: =E33/E6 -> 0.0030196143 | F34: =F33/F6 -> -0.0074434057 | G34: =G33/G6 -> -0.042429334 | H34: =H33/H6 -> -0.0075994792 | I34: =I33/I6 -> -0.049052155 | J34: =J33/J6 -> -0.011486935 | ... M34: =M33/M6 -> 0.71659566
B36: No. of Equity Shares | C36: =IFERROR('Data Sheet'!B93,0) -> 288.72 | D36: =IFERROR('Data Sheet'!C93,0) -> 288.73 | E36: =IFERROR('Data Sheet'!D93,0) -> 288.73 | F36: =IFERROR('Data Sheet'!E93,0) -> 288.73 | G36: =IFERROR('Data Sheet'!F93,0) -> 308.9 | H36: =IFERROR('Data Sheet'!G93,0) -> 332.03 | I36: =IFERROR('Data Sheet'!H93,0) -> 332.07 | J36: =IFERROR('Data Sheet'!I93,0) -> 332.13 | ... M36: =IFERROR('Data Sheet'!L93,0) -> 0
B38: Earning Per Share | C38: =IFERROR(C33/C36,0) -> 47.694444 | D38: =IFERROR(D33/D36,0) -> 14.527275 | E38: =IFERROR(E33/E36,0) -> 3.0491116 | F38: =IFERROR(F33/F36,0) -> -7.7839158 | G38: =IFERROR(G33/G36,0) -> -35.859307 | H38: =IFERROR(H33/H36,0) -> -5.7172846 | I38: =IFERROR(I33/I36,0) -> -41.132141 | J38: =IFERROR(J33/J36,0) -> -11.965495 | ... M38: =IFERROR(M33/M36,0) -> 0
B39: EPS Growth% | C39: =IFERROR(C38/B38-1,0) -> 0 | D39: =IFERROR(D38/C38-1,0) -> -0.6954095 | E39: =IFERROR(E38/D38-1,0) -> -0.79011124 | F39: =IFERROR(F38/E38-1,0) -> -3.5528471 | G39: =IFERROR(G38/F38-1,0) -> 3.6068468 | H39: =IFERROR(H38/G38-1,0) -> -0.84056344 | I39: =IFERROR(I38/H38-1,0) -> 6.194349 | J39: =IFERROR(J38/I38-1,0) -> -0.70909622 | ... M39: =IFERROR(M38/L38-1,0) -> -1
B41: Dividend Per Share | C41: =IFERROR('Data Sheet'!B31,0) -> 67.92 | D41: =IFERROR('Data Sheet'!C31,0) -> 0 | E41: =IFERROR('Data Sheet'!D31,0) -> 0 | F41: =IFERROR('Data Sheet'!E31,0) -> 0 | G41: =IFERROR('Data Sheet'!F31,0) -> 0 | H41: =IFERROR('Data Sheet'!G31,0) -> 0 | I41: =IFERROR('Data Sheet'!H31,0) -> 0 | J41: =IFERROR('Data Sheet'!I31,0) -> 766.02 | ... M41: =IFERROR('Data Sheet'!L31,0) -> 0
B42: Dividend Pay Out Ratio | C42: =IFERROR(C41/C36,0) -> 0.23524522 | D42: =IFERROR(D41/D36,0) -> 0 | E42: =IFERROR(E41/E36,0) -> 0 | F42: =IFERROR(F41/F36,0) -> 0 | G42: =IFERROR(G41/G36,0) -> 0 | H42: =IFERROR(H41/H36,0) -> 0 | I42: =IFERROR(I41/I36,0) -> 0 | J42: =IFERROR(J41/J36,0) -> 2.3063861 | ... M42: =IFERROR(M41/M36,0) -> 0
B44: Retained Earnings | C44: =IFERROR(1-C42,0) -> 0.76475478 | D44: =IFERROR(1-D42,0) -> 1 | E44: =IFERROR(1-E42,0) -> 1 | F44: =IFERROR(1-F42,0) -> 1 | G44: =IFERROR(1-G42,0) -> 1 | H44: =IFERROR(1-H42,0) -> 1 | I44: =IFERROR(1-I42,0) -> 1 | J44: =IFERROR(1-J42,0) -> -1.3063861 | ... M44: =IFERROR(1-M42,0) -> 1
A46: # | B46: BALANCE SHEET
B47: Equity Share Capital | C47: =IFERROR('Data Sheet'!B57,0) -> 679.18 | D47: =IFERROR('Data Sheet'!C57,0) -> 679.22 | E47: =IFERROR('Data Sheet'!D57,0) -> 679.22 | F47: =IFERROR('Data Sheet'!E57,0) -> 679.22 | G47: =IFERROR('Data Sheet'!F57,0) -> 719.54 | H47: =IFERROR('Data Sheet'!G57,0) -> 765.81 | I47: =IFERROR('Data Sheet'!H57,0) -> 765.88 | J47: =IFERROR('Data Sheet'!I57,0) -> 766.02 | ... M47: =IFERROR('Data Sheet'!L57,0) -> 0
B48: Reserves | C48: =IFERROR('Data Sheet'!B58,0) -> 78273.23 | D48: =IFERROR('Data Sheet'!C58,0) -> 57382.67 | E48: =IFERROR('Data Sheet'!D58,0) -> 94748.69 | F48: =IFERROR('Data Sheet'!E58,0) -> 59500.34 | G48: =IFERROR('Data Sheet'!F58,0) -> 62358.99 | H48: =IFERROR('Data Sheet'!G58,0) -> 54480.91 | I48: =IFERROR('Data Sheet'!H58,0) -> 43795.36 | J48: =IFERROR('Data Sheet'!I58,0) -> 44555.77 | ... M48: =IFERROR('Data Sheet'!L58,0) -> 0
B49: Borrowing | C49: =IFERROR('Data Sheet'!B59,0) -> 69359.96 | D49: =IFERROR('Data Sheet'!C59,0) -> 78603.98 | E49: =IFERROR('Data Sheet'!D59,0) -> 88950.47 | F49: =IFERROR('Data Sheet'!E59,0) -> 106175.34 | G49: =IFERROR('Data Sheet'!F59,0) -> 124787.64 | H49: =IFERROR('Data Sheet'!G59,0) -> 142130.57 | I49: =IFERROR('Data Sheet'!H59,0) -> 146449.03 | J49: =IFERROR('Data Sheet'!I59,0) -> 134113.44 | ... M49: =IFERROR('Data Sheet'!L59,0) -> 0
B50: Other Liabilities | C50: =IFERROR('Data Sheet'!B60,0) -> 114871.75 | D50: =IFERROR('Data Sheet'!C60,0) -> 135914.49 | E50: =IFERROR('Data Sheet'!D60,0) -> 142813.43 | F50: =IFERROR('Data Sheet'!E60,0) -> 139348.59 | G50: =IFERROR('Data Sheet'!F60,0) -> 132313.22 | H50: =IFERROR('Data Sheet'!G60,0) -> 144192.62 | I50: =IFERROR('Data Sheet'!H60,0) -> 138051.22 | J50: =IFERROR('Data Sheet'!I60,0) -> 155239.2 | ... M50: =IFERROR('Data Sheet'!L60,0) -> 0
B51: Total Lialbilities | C51: =IFERROR('Data Sheet'!B61,0) -> 263184.12 | D51: =IFERROR('Data Sheet'!C61,0) -> 272580.36 | E51: =IFERROR('Data Sheet'!D61,0) -> 327191.81 | F51: =IFERROR('Data Sheet'!E61,0) -> 305703.49 | G51: =IFERROR('Data Sheet'!F61,0) -> 320179.39 | H51: =IFERROR('Data Sheet'!G61,0) -> 341569.91 | I51: =IFERROR('Data Sheet'!H61,0) -> 329061.49 | J51: =IFERROR('Data Sheet'!I61,0) -> 334674.43 | ... M51: =IFERROR('Data Sheet'!L61,0) -> 0
B53: Fixed Asssets Net Block | C53: =IFERROR('Data Sheet'!B62,0) -> 107231.76 | D53: =IFERROR('Data Sheet'!C62,0) -> 95944.08 | E53: =IFERROR('Data Sheet'!D62,0) -> 121413.86 | F53: =IFERROR('Data Sheet'!E62,0) -> 111234.47 | G53: =IFERROR('Data Sheet'!F62,0) -> 127107.14 | H53: =IFERROR('Data Sheet'!G62,0) -> 138707.61 | I53: =IFERROR('Data Sheet'!H62,0) -> 138855.45 | J53: =IFERROR('Data Sheet'!I62,0) -> 132079.76 | ... M53: =IFERROR('Data Sheet'!L62,0) -> 0
B54: Capiital Work In Progress | C54: =IFERROR('Data Sheet'!B63,0) -> 25918.94 | D54: =IFERROR('Data Sheet'!C63,0) -> 33698.84 | E54: =IFERROR('Data Sheet'!D63,0) -> 40033.5 | F54: =IFERROR('Data Sheet'!E63,0) -> 31883.84 | G54: =IFERROR('Data Sheet'!F63,0) -> 35622.29 | H54: =IFERROR('Data Sheet'!G63,0) -> 20963.93 | I54: =IFERROR('Data Sheet'!H63,0) -> 10251.09 | J54: =IFERROR('Data Sheet'!I63,0) -> 14274.5 | ... M54: =IFERROR('Data Sheet'!L63,0) -> 0
B55: Investments | C55: =IFERROR('Data Sheet'!B64,0) -> 23767.02 | D55: =IFERROR('Data Sheet'!C64,0) -> 20337.92 | E55: =IFERROR('Data Sheet'!D64,0) -> 20812.75 | F55: =IFERROR('Data Sheet'!E64,0) -> 15770.72 | G55: =IFERROR('Data Sheet'!F64,0) -> 16308.48 | H55: =IFERROR('Data Sheet'!G64,0) -> 24620.28 | I55: =IFERROR('Data Sheet'!H64,0) -> 29379.53 | J55: =IFERROR('Data Sheet'!I64,0) -> 26379.16 | ... M55: =IFERROR('Data Sheet'!L64,0) -> 0
B56: Other Assets | C56: =IFERROR('Data Sheet'!B65-SUM('Data Sheet'!B67:B69),0) -> 29579.36 | D56: =IFERROR('Data Sheet'!C65-SUM('Data Sheet'!C67:C69),0) -> 37360.78 | E56: =IFERROR('Data Sheet'!D65-SUM('Data Sheet'!D67:D69),0) -> 48286.86 | F56: =IFERROR('Data Sheet'!E65-SUM('Data Sheet'!E67:E69),0) -> 56155.74 | G56: =IFERROR('Data Sheet'!F65-SUM('Data Sheet'!F67:F69),0) -> 58784.94 | H56: =IFERROR('Data Sheet'!G65-SUM('Data Sheet'!G67:G69),0) -> 61717.96 | I56: =IFERROR('Data Sheet'!H65-SUM('Data Sheet'!H67:H69),0) -> 62223.77 | J56: =IFERROR('Data Sheet'!I65-SUM('Data Sheet'!I67:I69),0) -> 68432.09 | ... L56: =IFERROR('Data Sheet'!K65-SUM('Data Sheet'!K67:K69),0) -> 58463 | M56: =IFERROR('Data Sheet'!L65,0) -> 0
B57: Total Non Current Asssets | C57: =IFERROR(SUM(C53:C56),0) -> 186497.08 | D57: =IFERROR(SUM(D53:D56),0) -> 187341.62 | E57: =IFERROR(SUM(E53:E56),0) -> 230546.97 | F57: =IFERROR(SUM(F53:F56),0) -> 215044.77 | G57: =IFERROR(SUM(G53:G56),0) -> 237822.85 | H57: =IFERROR(SUM(H53:H56),0) -> 246009.78 | I57: =IFERROR(SUM(I53:I56),0) -> 240709.84 | J57: =IFERROR(SUM(J53:J56),0) -> 241165.51 | ... M57: =IFERROR(SUM(M53:M56),0) -> 0
B59: Receivables | C59: =IFERROR('Data Sheet'!B67,0) -> 13570.91 | D59: =IFERROR('Data Sheet'!C67,0) -> 14075.55 | E59: =IFERROR('Data Sheet'!D67,0) -> 19893.3 | F59: =IFERROR('Data Sheet'!E67,0) -> 18996.17 | G59: =IFERROR('Data Sheet'!F67,0) -> 11172.69 | H59: =IFERROR('Data Sheet'!G67,0) -> 12679.08 | I59: =IFERROR('Data Sheet'!H67,0) -> 12442.12 | J59: =IFERROR('Data Sheet'!I67,0) -> 15737.97 | ... M59: =IFERROR('Data Sheet'!L67,0) -> 0
B60: Inventory | C60: =IFERROR('Data Sheet'!B68,0) -> 32655.73 | D60: =IFERROR('Data Sheet'!C68,0) -> 35085.31 | E60: =IFERROR('Data Sheet'!D68,0) -> 42137.63 | F60: =IFERROR('Data Sheet'!E68,0) -> 39013.73 | G60: =IFERROR('Data Sheet'!F68,0) -> 37456.88 | H60: =IFERROR('Data Sheet'!G68,0) -> 36088.59 | I60: =IFERROR('Data Sheet'!H68,0) -> 35240.34 | J60: =IFERROR('Data Sheet'!I68,0) -> 40755.39 | ... M60: =IFERROR('Data Sheet'!L68,0) -> 0
B61: Cash and Bank | C61: =IFERROR('Data Sheet'!B69,0) -> 30460.4 | D61: =IFERROR('Data Sheet'!C69,0) -> 36077.88 | E61: =IFERROR('Data Sheet'!D69,0) -> 34613.91 | F61: =IFERROR('Data Sheet'!E69,0) -> 32648.82 | G61: =IFERROR('Data Sheet'!F69,0) -> 33726.97 | H61: =IFERROR('Data Sheet'!G69,0) -> 46792.46 | I61: =IFERROR('Data Sheet'!H69,0) -> 40669.19 | J61: =IFERROR('Data Sheet'!I69,0) -> 37015.56 | ... M61: =IFERROR('Data Sheet'!L69,0) -> 0
B62: Total Current Assets | C62: =IFERROR(SUM(C59:C61),0) -> 76687.04 | D62: =IFERROR(SUM(D59:D61),0) -> 85238.74 | E62: =IFERROR(SUM(E59:E61),0) -> 96644.84 | F62: =IFERROR(SUM(F59:F61),0) -> 90658.72 | G62: =IFERROR(SUM(G59:G61),0) -> 82356.54 | H62: =IFERROR(SUM(H59:H61),0) -> 95560.13 | I62: =IFERROR(SUM(I59:I61),0) -> 88351.65 | J62: =IFERROR(SUM(J59:J61),0) -> 93508.92 | ... M62: =IFERROR(SUM(M59:M61),0) -> 0
B64: TOTAL ASSETS | C64: =IFERROR(SUM(C62,C57),0) -> 263184.12 | D64: =IFERROR(SUM(D62,D57),0) -> 272580.36 | E64: =IFERROR(SUM(E62,E57),0) -> 327191.81 | F64: =IFERROR(SUM(F62,F57),0) -> 305703.49 | G64: =IFERROR(SUM(G62,G57),0) -> 320179.39 | H64: =IFERROR(SUM(H62,H57),0) -> 341569.91 | I64: =IFERROR(SUM(I62,I57),0) -> 329061.49 | J64: =IFERROR(SUM(J62,J57),0) -> 334674.43 | ... M64: =IFERROR(SUM(M62,M57),0) -> 0
B66: CHECK | C66: =C64=C51 -> TRUE | D66: =D64=D51 -> TRUE | E66: =E64=E51 -> TRUE | F66: =F64=F51 -> TRUE | G66: =G64=G51 -> TRUE | H66: =H64=H51 -> TRUE | I66: =I64=I51 -> TRUE | J66: =J64=J51 -> TRUE | ... L66: =L64=L51 -> TRUE
A68: # | B68: CASH FLOW STATEMENT
B69: Operating Activities
B70: Profit from operations | C70: =IFERROR(CFS!E4,0) -> 38626 | D70: =IFERROR(CFS!F4,0) -> 28840 | E70: =IFERROR(CFS!G4,0) -> 33312 | F70: =IFERROR(CFS!H4,0) -> 28771 | G70: =IFERROR(CFS!I4,0) -> 23352 | H70: =IFERROR(CFS!J4,0) -> 31198 | I70: =IFERROR(CFS!K4,0) -> 26943 | J70: =IFERROR(CFS!L4,0) -> 41694 | ... L70: =IFERROR(CFS!N4,0) -> 58937
B71: Receivables | C71: =IFERROR(CFS!E5,0) -> -2223 | D71: =IFERROR(CFS!F5,0) -> -4152 | E71: =IFERROR(CFS!G5,0) -> -10688 | F71: =IFERROR(CFS!H5,0) -> -9109 | G71: =IFERROR(CFS!I5,0) -> 9950 | H71: =IFERROR(CFS!J5,0) -> -5505 | I71: =IFERROR(CFS!K5,0) -> 185 | J71: =IFERROR(CFS!L5,0) -> -2213 | ... L71: =IFERROR(CFS!N5,0) -> 3573
B72: Inventory | C72: =IFERROR(CFS!E6,0) -> -5743 | D72: =IFERROR(CFS!F6,0) -> -6621 | E72: =IFERROR(CFS!G6,0) -> -3560 | F72: =IFERROR(CFS!H6,0) -> 2069 | G72: =IFERROR(CFS!I6,0) -> 2326 | H72: =IFERROR(CFS!J6,0) -> 3814 | I72: =IFERROR(CFS!K6,0) -> 472 | J72: =IFERROR(CFS!L6,0) -> -5665 | ... L72: =IFERROR(CFS!N6,0) -> 2127
B73: Payables | C73: =IFERROR(CFS!E7,0) -> 3947 | D73: =IFERROR(CFS!F7,0) -> 9301 | E73: =IFERROR(CFS!G7,0) -> 7320 | F73: =IFERROR(CFS!H7,0) -> -4692 | G73: =IFERROR(CFS!I7,0) -> -8085 | H73: =IFERROR(CFS!J7,0) -> 5748 | I73: =IFERROR(CFS!K7,0) -> -7012 | J73: =IFERROR(CFS!L7,0) -> 6945 | ... L73: =IFERROR(CFS!N7,0) -> 1303
B74: Loans Advances | C74: =IFERROR(CFS!E8,0) -> -520 | D74: =IFERROR(CFS!F8,0) -> 0 | E74: =IFERROR(CFS!G8,0) -> 0 | F74: =IFERROR(CFS!H8,0) -> 0 | G74: =IFERROR(CFS!I8,0) -> 0 | H74: =IFERROR(CFS!J8,0) -> 0 | I74: =IFERROR(CFS!K8,0) -> 0 | J74: =IFERROR(CFS!L8,0) -> 0 | ... L74: =IFERROR(CFS!N8,0) -> 0
B75: Other WC items | C75: =IFERROR(CFS!E9,0) -> 5852 | D75: =IFERROR(CFS!F9,0) -> 4727 | E75: =IFERROR(CFS!G9,0) -> 494 | F75: =IFERROR(CFS!H9,0) -> 4512 | G75: =IFERROR(CFS!I9,0) -> 875 | H75: =IFERROR(CFS!J9,0) -> -4150 | I75: =IFERROR(CFS!K9,0) -> -4396 | J75: =IFERROR(CFS!L9,0) -> -2194 | ... L75: =IFERROR(CFS!N9,0) -> 1153
B76: Working capital changes | C76: =IFERROR(CFS!E10,0) -> 1313 | D76: =IFERROR(CFS!F10,0) -> 3254 | E76: =IFERROR(CFS!G10,0) -> -6434 | F76: =IFERROR(CFS!H10,0) -> -7221 | G76: =IFERROR(CFS!I10,0) -> 5065 | H76: =IFERROR(CFS!J10,0) -> -93 | I76: =IFERROR(CFS!K10,0) -> -10750 | J76: =IFERROR(CFS!L10,0) -> -3127 | ... L76: =IFERROR(CFS!N10,0) -> 8156
B77: Direct taxes | C77: =IFERROR(CFS!E11,0) -> -2040 | D77: =IFERROR(CFS!F11,0) -> -1895 | E77: =IFERROR(CFS!G11,0) -> -3021 | F77: =IFERROR(CFS!H11,0) -> -2659 | G77: =IFERROR(CFS!I11,0) -> -1785 | H77: =IFERROR(CFS!J11,0) -> -2105 | I77: =IFERROR(CFS!K11,0) -> -1910 | J77: =IFERROR(CFS!L11,0) -> -3179 | ... L77: =IFERROR(CFS!N11,0) -> -3991
B78: Cash from Operating Activities | C78: =IFERROR(SUM(C70:C77),0) -> 39212 | D78: =IFERROR(SUM(D70:D77),0) -> 33454 | E78: =IFERROR(SUM(E70:E77),0) -> 17423 | F78: =IFERROR(SUM(F70:F77),0) -> 11671 | G78: =IFERROR(SUM(G70:G77),0) -> 31698 | H78: =IFERROR(SUM(H70:H77),0) -> 28907 | I78: =IFERROR(SUM(I70:I77),0) -> 3532 | J78: =IFERROR(SUM(J70:J77),0) -> 32261 | ... L78: =IFERROR(SUM(L70:L77),0) -> 71258
B80: Investing Activities
B81: Fixed assets purchased | C81: =IFERROR(CFS!C13,0) -> -26975 | D81: =IFERROR(CFS!D13,0) -> -31962 | E81: =IFERROR(CFS!E13,0) -> -31503 | F81: =IFERROR(CFS!F13,0) -> -16072 | G81: =IFERROR(CFS!G13,0) -> -35079 | H81: =IFERROR(CFS!H13,0) -> -35304 | I81: =IFERROR(CFS!I13,0) -> -29702 | J81: =IFERROR(CFS!J13,0) -> -20205 | ... L81: =IFERROR(CFS!L13,0) -> -19230
B82: Fixed assets sold | C82: =IFERROR(CFS!C14,0) -> 50 | D82: =IFERROR(CFS!D14,0) -> 74 | E82: =IFERROR(CFS!E14,0) -> 59 | F82: =IFERROR(CFS!F14,0) -> 53 | G82: =IFERROR(CFS!G14,0) -> 30 | H82: =IFERROR(CFS!H14,0) -> 67 | I82: =IFERROR(CFS!I14,0) -> 171 | J82: =IFERROR(CFS!J14,0) -> 351 | ... L82: =IFERROR(CFS!L14,0) -> 285
B83: Investments purchased | C83: =IFERROR(CFS!C15,0) -> -429 | D83: =IFERROR(CFS!D15,0) -> -5461 | E83: =IFERROR(CFS!E15,0) -> -4728 | F83: =IFERROR(CFS!F15,0) -> -6 | G83: =IFERROR(CFS!G15,0) -> -329 | H83: =IFERROR(CFS!H15,0) -> -130 | I83: =IFERROR(CFS!I15,0) -> -1439 | J83: =IFERROR(CFS!J15,0) -> -7530 | ... L83: =IFERROR(CFS!L15,0) -> -50
B84: Investments sold | C84: =IFERROR(CFS!C16,0) -> 4 | D84: =IFERROR(CFS!D16,0) -> 42 | E84: =IFERROR(CFS!E16,0) -> 89 | F84: =IFERROR(CFS!F16,0) -> 1965 | G84: =IFERROR(CFS!G16,0) -> 2381 | H84: =IFERROR(CFS!H16,0) -> 5644 | I84: =IFERROR(CFS!I16,0) -> 21 | J84: =IFERROR(CFS!J16,0) -> 226 | ... L84: =IFERROR(CFS!L16,0) -> 6895
B85: Interest received | C85: =IFERROR(CFS!C17,0) -> 653 | D85: =IFERROR(CFS!D17,0) -> 698 | E85: =IFERROR(CFS!E17,0) -> 731 | F85: =IFERROR(CFS!F17,0) -> 638 | G85: =IFERROR(CFS!G17,0) -> 690 | H85: =IFERROR(CFS!H17,0) -> 761 | I85: =IFERROR(CFS!I17,0) -> 1104 | J85: =IFERROR(CFS!J17,0) -> 428 | ... L85: =IFERROR(CFS!L17,0) -> 973
B86: Dividends received | C86: =IFERROR(CFS!C18,0) -> 40 | D86: =IFERROR(CFS!D18,0) -> 80 | E86: =IFERROR(CFS!E18,0) -> 58 | F86: =IFERROR(CFS!F18,0) -> 620 | G86: =IFERROR(CFS!G18,0) -> 1797 | H86: =IFERROR(CFS!H18,0) -> 232 | I86: =IFERROR(CFS!I18,0) -> 21 | J86: =IFERROR(CFS!J18,0) -> 18 | ... L86: =IFERROR(CFS!L18,0) -> 46
B87: Investment in group cos | C87: =IFERROR(CFS!C19,0) -> 0 | D87: =IFERROR(CFS!D19,0) -> -160 | E87: =IFERROR(CFS!E19,0) -> 0 | F87: =IFERROR(CFS!F19,0) -> -107 | G87: =IFERROR(CFS!G19,0) -> -4 | H87: =IFERROR(CFS!H19,0) -> -9 | I87: =IFERROR(CFS!I19,0) -> -606 | J87: =IFERROR(CFS!J19,0) -> -10 | ... L87: =IFERROR(CFS!L19,0) -> 0
B88: Redemp n Canc of Shares | C88: =IFERROR(CFS!C20,0) -> 0 | D88: =IFERROR(CFS!D20,0) -> 0 | E88: =IFERROR(CFS!E20,0) -> 0 | F88: =IFERROR(CFS!F20,0) -> 0 | G88: =IFERROR(CFS!G20,0) -> 14 | H88: =IFERROR(CFS!H20,0) -> 533 | I88: =IFERROR(CFS!I20,0) -> 0 | J88: =IFERROR(CFS!J20,0) -> 0 | ... L88: =IFERROR(CFS!L20,0) -> 19
B89: Acquisition of companies | C89: =IFERROR(CFS!C21,0) -> -185 | D89: =IFERROR(CFS!D21,0) -> 0 | E89: =IFERROR(CFS!E21,0) -> -111 | F89: =IFERROR(CFS!F21,0) -> 0 | G89: =IFERROR(CFS!G21,0) -> 0 | H89: =IFERROR(CFS!H21,0) -> -8 | I89: =IFERROR(CFS!I21,0) -> -27 | J89: =IFERROR(CFS!J21,0) -> 0 | ... L89: =IFERROR(CFS!L21,0) -> 0
B90: Inter corporate deposits | C90: =IFERROR(CFS!C22,0) -> 0 | D90: =IFERROR(CFS!D22,0) -> 0 | E90: =IFERROR(CFS!E22,0) -> 0 | F90: =IFERROR(CFS!F22,0) -> 0 | G90: =IFERROR(CFS!G22,0) -> 0 | H90: =IFERROR(CFS!H22,0) -> 0 | I90: =IFERROR(CFS!I22,0) -> 0 | J90: =IFERROR(CFS!J22,0) -> 0 | ... L90: =IFERROR(CFS!L22,0) -> 0
B91: Other investing items | C91: =IFERROR(CFS!C23,0) -> -1149 | D91: =IFERROR(CFS!D23,0) -> 456 | E91: =IFERROR(CFS!E23,0) -> -1289 | F91: =IFERROR(CFS!F23,0) -> -26663 | G91: =IFERROR(CFS!G23,0) -> 5360 | H91: =IFERROR(CFS!H23,0) -> 7335 | I91: =IFERROR(CFS!I23,0) -> -2659 | J91: =IFERROR(CFS!J23,0) -> 1051 | ... L91: =IFERROR(CFS!L23,0) -> -4357
B92: Cash from Investing Activities | C92: =SUM(C81:C91) -> -27991 | D92: =SUM(D81:D91) -> -36233 | E92: =SUM(E81:E91) -> -36694 | F92: =SUM(F81:F91) -> -39572 | G92: =SUM(G81:G91) -> -25140 | H92: =SUM(H81:H91) -> -20879 | I92: =SUM(I81:I91) -> -33116 | J92: =SUM(J81:J91) -> -25671 | ... L92: =SUM(L81:L91) -> -15419
B94: Financing Activities
B95: Proceeds from shares | C95: =IFERROR(CFS!C25,0) -> 0 | D95: =IFERROR(CFS!D25,0) -> 0 | E95: =IFERROR(CFS!E25,0) -> 7433 | F95: =IFERROR(CFS!F25,0) -> 5 | G95: =IFERROR(CFS!G25,0) -> 0 | H95: =IFERROR(CFS!H25,0) -> 0 | I95: =IFERROR(CFS!I25,0) -> 3889 | J95: =IFERROR(CFS!J25,0) -> 2603 | ... L95: =IFERROR(CFS!L25,0) -> 20
B96: Redemption of debentures | C96: =IFERROR(CFS!C26,0) -> -658 | D96: =IFERROR(CFS!D26,0) -> -744 | E96: =IFERROR(CFS!E26,0) -> 0 | F96: =IFERROR(CFS!F26,0) -> 0 | G96: =IFERROR(CFS!G26,0) -> 0 | H96: =IFERROR(CFS!H26,0) -> 0 | I96: =IFERROR(CFS!I26,0) -> 0 | J96: =IFERROR(CFS!J26,0) -> 0 | ... L96: =IFERROR(CFS!L26,0) -> 0
B97: Proceeds from borrowings | C97: =IFERROR(CFS!C27,0) -> 33258 | D97: =IFERROR(CFS!D27,0) -> 36363 | E97: =IFERROR(CFS!E27,0) -> 19519 | F97: =IFERROR(CFS!F27,0) -> 33390 | G97: =IFERROR(CFS!G27,0) -> 37482 | H97: =IFERROR(CFS!H27,0) -> 51128 | I97: =IFERROR(CFS!I27,0) -> 38297 | J97: =IFERROR(CFS!J27,0) -> 46641 | ... L97: =IFERROR(CFS!L27,0) -> 43934
B98: Repayment of borrowings | C98: =IFERROR(CFS!C28,0) -> -29141 | D98: =IFERROR(CFS!D28,0) -> -23332 | E98: =IFERROR(CFS!E28,0) -> -24924 | F98: =IFERROR(CFS!F28,0) -> -21732 | G98: =IFERROR(CFS!G28,0) -> -29964 | H98: =IFERROR(CFS!H28,0) -> -35198 | I98: =IFERROR(CFS!I28,0) -> -29847 | J98: =IFERROR(CFS!J28,0) -> -29709 | ... L98: =IFERROR(CFS!L28,0) -> -62557
B99: Interest paid fin | C99: =IFERROR(CFS!C29,0) -> -6171 | D99: =IFERROR(CFS!D29,0) -> -6307 | E99: =IFERROR(CFS!E29,0) -> -5716 | F99: =IFERROR(CFS!F29,0) -> -5336 | G99: =IFERROR(CFS!G29,0) -> -5411 | H99: =IFERROR(CFS!H29,0) -> -7005 | I99: =IFERROR(CFS!I29,0) -> -7518 | J99: =IFERROR(CFS!J29,0) -> -8123 | ... L99: =IFERROR(CFS!L29,0) -> -9336
B100: Dividends paid | C100: =IFERROR(CFS!C30,0) -> -722 | D100: =IFERROR(CFS!D30,0) -> -720 | E100: =IFERROR(CFS!E30,0) -> -108 | F100: =IFERROR(CFS!F30,0) -> -121 | G100: =IFERROR(CFS!G30,0) -> -96 | H100: =IFERROR(CFS!H30,0) -> -95 | I100: =IFERROR(CFS!I30,0) -> -57 | J100: =IFERROR(CFS!J30,0) -> -30 | ... L100: =IFERROR(CFS!L30,0) -> -141
B101: Financial liabilities | C101: =IFERROR(CFS!C31,0) -> 0 | D101: =IFERROR(CFS!D31,0) -> 0 | E101: =IFERROR(CFS!E31,0) -> 0 | F101: =IFERROR(CFS!F31,0) -> 0 | G101: =IFERROR(CFS!G31,0) -> 0 | H101: =IFERROR(CFS!H31,0) -> 0 | I101: =IFERROR(CFS!I31,0) -> -1346 | J101: =IFERROR(CFS!J31,0) -> -1477 | ... L101: =IFERROR(CFS!L31,0) -> -1517
B102: Other financing items | C102: =IFERROR(CFS!C32,0) -> -450 | D102: =IFERROR(CFS!D32,0) -> -57 | E102: =IFERROR(CFS!E32,0) -> 0 | F102: =IFERROR(CFS!F32,0) -> 0 | G102: =IFERROR(CFS!G32,0) -> 0 | H102: =IFERROR(CFS!H32,0) -> 0 | I102: =IFERROR(CFS!I32,0) -> -29 | J102: =IFERROR(CFS!J32,0) -> 0 | ... L102: =IFERROR(CFS!L32,0) -> 3355
B103: Cash from Financing Activities | C103: =SUM(C95:C102) -> -3884 | D103: =SUM(D95:D102) -> 5203 | E103: =SUM(E95:E102) -> -3796 | F103: =SUM(F95:F102) -> 6206 | G103: =SUM(G95:G102) -> 2011 | H103: =SUM(H95:H102) -> 8830 | I103: =SUM(I95:I102) -> 3389 | J103: =SUM(J95:J102) -> 9905 | ... L103: =SUM(L95:L102) -> -26242
B105: Net Cash Flow | C105: =IFERROR(SUM(C78,C92,C103),0) -> 7337 | D105: =IFERROR(SUM(D78,D92,D103),0) -> 2424 | E105: =IFERROR(SUM(E78,E92,E103),0) -> -23067 | F105: =IFERROR(SUM(F78,F92,F103),0) -> -21695 | G105: =IFERROR(SUM(G78,G92,G103),0) -> 8569 | H105: =IFERROR(SUM(H78,H92,H103),0) -> 16858 | I105: =IFERROR(SUM(I78,I92,I103),0) -> -26195 | J105: =IFERROR(SUM(J78,J92,J103),0) -> 16495 | ... L105: =IFERROR(SUM(L78,L92,L103),0) -> 29597

Sheet Ratio Anaysis
B2: ="RATIO ANALYSIS -"&'Data Sheet'!B1 -> RATIO ANALYSIS -TATA MOTORS LTD
B3: YEARS | C3: ='Data Sheet'!B16 -> 42460 | D3: ='Data Sheet'!C16 -> 42825 | E3: ='Data Sheet'!D16 -> 43190 | F3: ='Data Sheet'!E16 -> 43555 | G3: ='Data Sheet'!F16 -> 43921 | H3: ='Data Sheet'!G16 -> 44286 | I3: ='Data Sheet'!H16 -> 44651 | J3: ='Data Sheet'!I16 -> 45016 | ... L3: ='Data Sheet'!K16 -> 45747 | M3: Trend | N3: Mean | O3: Median
B5: Sales Growth | C5: =IFERROR('Historical FS'!C7,0) -> - | D5: =IFERROR('Historical FS'!D7,0) -> -0.01228033 | E5: =IFERROR('Historical FS'!E7,0) -> 0.081047746 | F5: =IFERROR('Historical FS'!F7,0) -> 0.035629919 | G5: =IFERROR('Historical FS'!G7,0) -> -0.13536016 | H5: =IFERROR('Historical FS'!H7,0) -> -0.043181168 | I5: =IFERROR('Historical FS'!I7,0) -> 0.11472967 | J5: =IFERROR('Historical FS'!J7,0) -> 0.24245815 | ... L5: =IFERROR('Historical FS'!L7,0) -> 0.013084771 | N5: =IFERROR(AVERAGE(D5:L5),0) -> 0.061181096 | O5: =IFERROR(MEDIAN(C5:L5),0) -> 0.035629919
B6: EBITDA Growth | C6: - | D6: =IFERROR('Historical FS'!D18/'Historical FS'!C18-1,0) -> -0.22936587 | E6: =IFERROR('Historical FS'!E18/'Historical FS'!D18-1,0) -> 0.063165689 | F6: =IFERROR('Historical FS'!F18/'Historical FS'!E18-1,0) -> -0.21595203 | G6: =IFERROR('Historical FS'!G18/'Historical FS'!F18-1,0) -> -0.27072538 | H6: =IFERROR('Historical FS'!H18/'Historical FS'!G18-1,0) -> 0.79503554 | I6: =IFERROR('Historical FS'!I18/'Historical FS'!H18-1,0) -> -0.23437418 | J6: =IFERROR('Historical FS'!J18/'Historical FS'!I18-1,0) -> 0.28704224 | K6: =IFERROR('Historical FS'!K18/'Historical FS'!J18-1,0) -> 0.81746176 | L6: =IFERROR('Historical FS'!L18/'Historical FS'!K18-1,0) -> -0.04510238 | N6: =IFERROR(AVERAGE(D6:L6),0) -> 0.10746504 | O6: =IFERROR(MEDIAN(C6:L6),0) -> -0.04510238
B7: EBIT Growth | C7: - | D7: =IFERROR('Historical FS'!D27/'Historical FS'!C27-1,0) -> -0.55668252 | E7: =IFERROR('Historical FS'!E27/'Historical FS'!D27-1,0) -> -0.29861437 | F7: =IFERROR('Historical FS'!F27/'Historical FS'!E27-1,0) -> -1.8970951 | G7: =IFERROR('Historical FS'!G27/'Historical FS'!F27-1,0) -> 1.2800252 | H7: =IFERROR('Historical FS'!H27/'Historical FS'!G27-1,0) -> -1.060248 | I7: =IFERROR('Historical FS'!I27/'Historical FS'!H27-1,0) -> -15.649149 | J7: =IFERROR('Historical FS'!J27/'Historical FS'!I27-1,0) -> -0.65313669 | K7: =IFERROR('Historical FS'!K27/'Historical FS'!J27-1,0) -> -8.0308008 | L7: =IFERROR('Historical FS'!L27/'Historical FS'!K27-1,0) -> 0.16902266 | N7: =IFERROR(AVERAGE(D7:L7),0) -> -2.9662977 | O7: =IFERROR(MEDIAN(C7:L7),0) -> -0.65313669
B8: Net Profit Growth | C8: - | D8: =IFERROR('Historical FS'!D33/'Historical FS'!C33-1,0) -> -0.69539895 | E8: =IFERROR('Historical FS'!E33/'Historical FS'!D33-1,0) -> -0.79011124 | F8: =IFERROR('Historical FS'!F33/'Historical FS'!E33-1,0) -> -3.5528471 | G8: =IFERROR('Historical FS'!G33/'Historical FS'!F33-1,0) -> 3.9286703 | H8: =IFERROR('Historical FS'!H33/'Historical FS'!G33-1,0) -> -0.82862505 | I8: =IFERROR('Historical FS'!I33/'Historical FS'!H33-1,0) -> 6.1952157 | J8: =IFERROR('Historical FS'!J33/'Historical FS'!I33-1,0) -> -0.70904365 | K8: =IFERROR('Historical FS'!K33/'Historical FS'!J33-1,0) -> -7.7977655 | L8: =IFERROR('Historical FS'!L33/'Historical FS'!K33-1,0) -> -0.39385527 | N8: =IFERROR(AVERAGE(D8:L8),0) -> -0.51597342 | O8: =IFERROR(MEDIAN(C8:L8),0) -> -0.70904365
B9: Dividend Growth | C9: - | D9: =IFERROR('Historical FS'!D41/'Historical FS'!C41-1,0) -> -1 | E9: =IFERROR('Historical FS'!E41/'Historical FS'!D41-1,0) -> 0 | F9: =IFERROR('Historical FS'!F41/'Historical FS'!E41-1,0) -> 0 | G9: =IFERROR('Historical FS'!G41/'Historical FS'!F41-1,0) -> 0 | H9: =IFERROR('Historical FS'!H41/'Historical FS'!G41-1,0) -> 0 | I9: =IFERROR('Historical FS'!I41/'Historical FS'!H41-1,0) -> 0 | J9: =IFERROR('Historical FS'!J41/'Historical FS'!I41-1,0) -> 0 | K9: =IFERROR('Historical FS'!K41/'Historical FS'!J41-1,0) -> 2.003838 | L9: =IFERROR('Historical FS'!L41/'Historical FS'!K41-1,0) -> -0.04041721 | N9: =IFERROR(AVERAGE(D9:L9),0) -> 0.10704676 | O9: =IFERROR(MEDIAN(C9:L9),0) -> 0
B12: Gross Margin | C12: =IFERROR('Historical FS'!C13,0) -> 0.24734524 | D12: =IFERROR('Historical FS'!D13,0) -> 0.23819078 | E12: =IFERROR('Historical FS'!E13,0) -> 0.2164999 | F12: =IFERROR('Historical FS'!F13,0) -> 0.19571167 | G12: =IFERROR('Historical FS'!G13,0) -> 0.19417127 | H12: =IFERROR('Historical FS'!H13,0) -> 0.21805386 | I12: =IFERROR('Historical FS'!I13,0) -> 0.19807108 | J12: =IFERROR('Historical FS'!J13,0) -> 0.20685018 | ... L12: =IFERROR('Historical FS'!L13,0) -> 0.2248968 | N12: =IFERROR(AVERAGE(C12:L12),0) -> 0.21693584 | O12: =IFERROR(MEDIAN(C12:L12),0) -> 0.21727688
B13: EBITDA Margin | C13: =IFERROR('Historical FS'!C19,0) -> 0.14061845 | D13: =IFERROR('Historical FS'!D19,0) -> 0.10971269 | E13: =IFERROR('Historical FS'!E19,0) -> 0.10789788 | F13: =IFERROR('Historical FS'!F19,0) -> 0.081686629 | G13: =IFERROR('Historical FS'!G19,0) -> 0.068898034 | H13: =IFERROR('Historical FS'!H19,0) -> 0.12925584 | I13: =IFERROR('Historical FS'!I19,0) -> 0.088776328 | J13: =IFERROR('Historical FS'!J19,0) -> 0.091961958 | ... L13: =IFERROR('Historical FS'!L19,0) -> 0.12557796 | N13: =IFERROR(AVERAGE(C13:L13),0) -> 0.10776159 | O13: =IFERROR(MEDIAN(C13:L13),0) -> 0.10880529
B14: EBIT Margin | C14: =IFERROR(('Historical FS'!C18-'Historical FS'!C24)/'Historical FS'!C6,0) -> 0.079417028 | D14: =IFERROR(('Historical FS'!D18-'Historical FS'!D24)/'Historical FS'!D6,0) -> 0.043322301 | E14: =IFERROR(('Historical FS'!E18-'Historical FS'!E24)/'Historical FS'!E6,0) -> 0.033970412 | F14: =IFERROR(('Historical FS'!F18-'Historical FS'!F24)/'Historical FS'!F6,0) -> 0.0035560233 | G14: =IFERROR(('Historical FS'!G18-'Historical FS'!G24)/'Historical FS'!G6,0) -> -0.013170363 | H14: =IFERROR(('Historical FS'!H18-'Historical FS'!H24)/'Historical FS'!H6,0) -> 0.034991608 | I14: =IFERROR(('Historical FS'!I18-'Historical FS'!I24)/'Historical FS'!I6,0) -> -0.00041514993 | J14: =IFERROR(('Historical FS'!J18-'Historical FS'!J24)/'Historical FS'!J6,0) -> 0.020104347 | ... L14: =IFERROR(('Historical FS'!L18-'Historical FS'!L24)/'Historical FS'!L6,0) -> 0.072686749 | N14: =IFERROR(AVERAGE(C14:L14),0) -> 0.034493271 | O14: =IFERROR(MEDIAN(C14:L14),0) -> 0.03448101
B15: EBT Margin | C15: =IFERROR('Historical FS'!C28,0) -> 0.061511301 | D15: =IFERROR('Historical FS'!D28,0) -> 0.027608071 | E15: =IFERROR('Historical FS'!E28,0) -> 0.017912164 | F15: =IFERROR('Historical FS'!F28,0) -> -0.015516079 | G15: =IFERROR('Historical FS'!G28,0) -> -0.04091536 | H15: =IFERROR('Historical FS'!H28,0) -> 0.0025763152 | I15: =IFERROR('Historical FS'!I28,0) -> -0.033856482 | J15: =IFERROR('Historical FS'!J28,0) -> -0.009451885 | ... L15: =IFERROR('Historical FS'!L28,0) -> 0.061126463 | N15: =IFERROR(AVERAGE(C15:L15),0) -> 0.012396721 | O15: =IFERROR(MEDIAN(C15:L15),0) -> 0.01024424
B16: Net Profit Margin | C16: =IFERROR('Historical FS'!C34,0) -> 0.050432382 | D16: =IFERROR('Historical FS'!D34,0) -> 0.015552749 | E16: =IFERROR('Historical FS'!E34,0) -> 0.0030196143 | F16: =IFERROR('Historical FS'!F34,0) -> -0.0074434057 | G16: =IFERROR('Historical FS'!G34,0) -> -0.042429334 | H16: =IFERROR('Historical FS'!H34,0) -> -0.0075994792 | I16: =IFERROR('Historical FS'!I34,0) -> -0.049052155 | J16: =IFERROR('Historical FS'!J34,0) -> -0.011486935 | ... L16: =IFERROR('Historical FS'!L34,0) -> 0.037241724 | N16: =IFERROR(AVERAGE(C16:L16),0) -> 0.0050479411 | O16: =IFERROR(MEDIAN(C16:L16),0) -> -0.0022118957
B19: SalesExpenses%Sales | C19: =IFERROR('Historical FS'!C16,0) -> 0.10672679 | D19: =IFERROR('Historical FS'!D16,0) -> 0.1284781 | E19: =IFERROR('Historical FS'!E16,0) -> 0.10860202 | F19: =IFERROR('Historical FS'!F16,0) -> 0.11402505 | G19: =IFERROR('Historical FS'!G16,0) -> 0.12527324 | H19: =IFERROR('Historical FS'!H16,0) -> 0.088798023 | I19: =IFERROR('Historical FS'!I16,0) -> 0.10929475 | J19: =IFERROR('Historical FS'!J16,0) -> 0.11488822 | ... L19: =IFERROR('Historical FS'!L16,0) -> 0.099318846 | N19: =IFERROR(AVERAGE(C19:L19),0) -> 0.10917425 | O19: =IFERROR(MEDIAN(C19:L19),0) -> 0.10894839
B20: Depriciation%Sales | C20: =IFERROR('Historical FS'!C25,0) -> 0.061201426 | D20: =IFERROR('Historical FS'!D25,0) -> 0.066390387 | E20: =IFERROR('Historical FS'!E25,0) -> 0.073927472 | F20: =IFERROR('Historical FS'!F25,0) -> 0.078130605 | G20: =IFERROR('Historical FS'!G25,0) -> 0.082068398 | H20: =IFERROR('Historical FS'!H25,0) -> 0.094264231 | I20: =IFERROR('Historical FS'!I25,0) -> 0.089191478 | J20: =IFERROR('Historical FS'!J25,0) -> 0.071857611 | ... L20: =IFERROR('Historical FS'!L25,0) -> 0.052891209 | N20: =IFERROR(AVERAGE(C20:L20),0) -> 0.073268318 | O20: =IFERROR(MEDIAN(C20:L20),0) -> 0.072892542
B21: OperatingIncome%Sales | C21: =IFERROR('Ratio Anaysis'!C13,0) -> 0.14061845 | D21: =IFERROR('Ratio Anaysis'!D13,0) -> 0.10971269 | E21: =IFERROR('Ratio Anaysis'!E13,0) -> 0.10789788 | F21: =IFERROR('Ratio Anaysis'!F13,0) -> 0.081686629 | G21: =IFERROR('Ratio Anaysis'!G13,0) -> 0.068898034 | H21: =IFERROR('Ratio Anaysis'!H13,0) -> 0.12925584 | I21: =IFERROR('Ratio Anaysis'!I13,0) -> 0.088776328 | J21: =IFERROR('Ratio Anaysis'!J13,0) -> 0.091961958 | ... L21: =IFERROR('Ratio Anaysis'!L13,0) -> 0.12557796 | N21: =IFERROR(AVERAGE(C21:L21),0) -> 0.10776159 | O21: =IFERROR(MEDIAN(C21:L21),0) -> 0.10880529
B23: Return on Capital Employed | C23: =IFERROR((('Historical FS'!C18-'Historical FS'!C24)/SUM('Historical FS'!C47,'Historical FS'!C48,'Historical FS'!C49)),0) -> 0.1462081 | D23: =IFERROR((('Historical FS'!D18-'Historical FS'!D24)/SUM('Historical FS'!D47,'Historical FS'!D48,'Historical FS'!D49)),0) -> 0.085490986 | E23: =IFERROR((('Historical FS'!E18-'Historical FS'!E24)/SUM('Historical FS'!E47,'Historical FS'!E48,'Historical FS'!E49)),0) -> 0.053716114 | F23: =IFERROR((('Historical FS'!F18-'Historical FS'!F24)/SUM('Historical FS'!F47,'Historical FS'!F48,'Historical FS'!F49)),0) -> 0.0064542734 | G23: =IFERROR((('Historical FS'!G18-'Historical FS'!G24)/SUM('Historical FS'!G47,'Historical FS'!G48,'Historical FS'!G49)),0) -> -0.018302178 | H23: =IFERROR((('Historical FS'!H18-'Historical FS'!H24)/SUM('Historical FS'!H47,'Historical FS'!H48,'Historical FS'!H49)),0) -> 0.044284325 | I23: =IFERROR((('Historical FS'!I18-'Historical FS'!I24)/SUM('Historical FS'!I47,'Historical FS'!I48,'Historical FS'!I49)),0) -> -0.00060520306 | J23: =IFERROR((('Historical FS'!J18-'Historical FS'!J24)/SUM('Historical FS'!J47,'Historical FS'!J48,'Historical FS'!J49)),0) -> 0.038762956 | ... L23: =IFERROR((('Historical FS'!L18-'Historical FS'!L24)/SUM('Historical FS'!L47,'Historical FS'!L48,'Historical FS'!L49)),0) -> 0.17028623 | N23: =IFERROR(AVERAGE(C23:L23),0) -> 0.068544162 | O23: =IFERROR(MEDIAN(C23:L23),0) -> 0.049000219
B24: Retained Earnings % | C24: =IFERROR('Historical FS'!C44,0) -> 0.76475478 | D24: =IFERROR('Historical FS'!D44,0) -> 1 | E24: =IFERROR('Historical FS'!E44,0) -> 1 | F24: =IFERROR('Historical FS'!F44,0) -> 1 | G24: =IFERROR('Historical FS'!G44,0) -> 1 | H24: =IFERROR('Historical FS'!H44,0) -> 1 | I24: =IFERROR('Historical FS'!I44,0) -> 1 | J24: =IFERROR('Historical FS'!J44,0) -> -1.3063861 | ... L24: =IFERROR('Historical FS'!L44,0) -> -4.9978812 | N24: =IFERROR(AVERAGE(C24:L24),0) -> -0.54625199 | O24: =IFERROR(MEDIAN(C24:L24),0) -> 1
B25: Return on Equity % | C25: =IFERROR('Historical FS'!C33/SUM('Historical FS'!C47:C48),0) -> 0.17441317 | D25: =IFERROR('Historical FS'!D33/SUM('Historical FS'!D47:D48),0) -> 0.07224119 | E25: =IFERROR('Historical FS'!E33/SUM('Historical FS'!E47:E48),0) -> 0.0092254981 | F25: =IFERROR('Historical FS'!F33/SUM('Historical FS'!F47:F48),0) -> -0.037345737 | G25: =IFERROR('Historical FS'!G33/SUM('Historical FS'!G47:G48),0) -> -0.17560555 | H25: =IFERROR('Historical FS'!H33/SUM('Historical FS'!H47:H48),0) -> -0.034360592 | I25: =IFERROR('Historical FS'!I33/SUM('Historical FS'!I47:I48),0) -> -0.30651638 | J25: =IFERROR('Historical FS'!J33/SUM('Historical FS'!J47:J48),0) -> -0.087686298 | ... L25: =IFERROR('Historical FS'!L33/SUM('Historical FS'!L47:L48),0) -> 0.14098877 | N25: =IFERROR(AVERAGE(C25:L25),0) -> 0.0073484502 | O25: =IFERROR(MEDIAN(C25:L25),0) -> -0.012567547
B26: Self Sustained Growth Rate | C26: =IFERROR(C24*C25,0) -> 0.1333833 | D26: =IFERROR(D24*D25,0) -> 0.07224119 | E26: =IFERROR(E24*E25,0) -> 0.0092254981 | F26: =IFERROR(F24*F25,0) -> -0.037345737 | G26: =IFERROR(G24*G25,0) -> -0.17560555 | H26: =IFERROR(H24*H25,0) -> -0.034360592 | I26: =IFERROR(I24*I25,0) -> -0.30651638 | J26: =IFERROR(J24*J25,0) -> 0.11455216 | ... L26: =IFERROR(L24*L25,0) -> -0.70464513 | N26: =IFERROR(AVERAGE(C26:L26),0) -> -0.28133602 | O26: =IFERROR(MEDIAN(C26:L26),0) -> -0.035853164
B27: Interest Coverage Ratio | C27: =IFERROR(('Historical FS'!C18-'Historical FS'!C24)/'Historical FS'!C21,0) -> 4.4352864 | D27: =IFERROR(('Historical FS'!D18-'Historical FS'!D24)/'Historical FS'!D21,0) -> 2.7568835 | E27: =IFERROR(('Historical FS'!E18-'Historical FS'!E24)/'Historical FS'!E21,0) -> 2.1154494 | F27: =IFERROR(('Historical FS'!F18-'Historical FS'!F24)/'Historical FS'!F21,0) -> 0.18645157 | G27: =IFERROR(('Historical FS'!G18-'Historical FS'!G24)/'Historical FS'!G21,0) -> -0.47469327 | H27: =IFERROR(('Historical FS'!H18-'Historical FS'!H24)/'Historical FS'!H21,0) -> 1.0794784 | I27: =IFERROR(('Historical FS'!I18-'Historical FS'!I24)/'Historical FS'!I21,0) -> -0.012414276 | J27: =IFERROR(('Historical FS'!J18-'Historical FS'!J24)/'Historical FS'!J21,0) -> 0.6802067 | ... L27: =IFERROR(('Historical FS'!L18-'Historical FS'!L24)/'Historical FS'!L21,0) -> 6.2876254 | N27: =IFERROR(AVERAGE(C27:L27),0) -> 2.1081796 | O27: =IFERROR(MEDIAN(C27:L27),0) -> 1.5974639
B29: Debtor Turnover Ratio | C29: =IFERROR('Historical FS'!C6/'Historical FS'!C59,0) -> 20.119918 | D29: =IFERROR('Historical FS'!D6/'Historical FS'!D59,0) -> 19.160353 | E29: =IFERROR('Historical FS'!E6/'Historical FS'!E59,0) -> 14.655712 | F29: =IFERROR('Historical FS'!F6/'Historical FS'!F59,0) -> 15.894699 | G29: =IFERROR('Historical FS'!G6/'Historical FS'!G59,0) -> 23.366617 | H29: =IFERROR('Historical FS'!H6/'Historical FS'!H59,0) -> 19.701331 | I29: =IFERROR('Historical FS'!I6/'Historical FS'!I59,0) -> 22.379918 | J29: =IFERROR('Historical FS'!J6/'Historical FS'!J59,0) -> 21.982948 | ... L29: =IFERROR('Historical FS'!L6/'Historical FS'!L59,0) -> 33.189538 | N29: =IFERROR(AVERAGE(C29:L29),0) -> 21.605368 | O29: =IFERROR(MEDIAN(C29:L29),0) -> 21.051433
B30: Creditor Turnover Ratio | C30: =IFERROR('Historical FS'!C6/'Historical FS'!C50,0) -> 2.3769604 | D30: =IFERROR('Historical FS'!D6/'Historical FS'!D50,0) -> 1.9842808 | E30: =IFERROR('Historical FS'!E6/'Historical FS'!E50,0) -> 2.041478 | F30: =IFERROR('Historical FS'!F6/'Historical FS'!F50,0) -> 2.1667848 | G30: =IFERROR('Historical FS'!G6/'Historical FS'!G50,0) -> 1.9731057 | H30: =IFERROR('Historical FS'!H6/'Historical FS'!H50,0) -> 1.7323685 | I30: =IFERROR('Historical FS'!I6/'Historical FS'!I50,0) -> 2.0170312 | J30: =IFERROR('Historical FS'!J6/'Historical FS'!J50,0) -> 2.2286057 | ... L30: =IFERROR('Historical FS'!L6/'Historical FS'!L50,0) -> 2.3228767 | N30: =IFERROR(AVERAGE(C30:L30),0) -> 2.1290872 | O30: =IFERROR(MEDIAN(C30:L30),0) -> 2.1041314
B31: Inventory Turnover | C31: =IFERROR('Historical FS'!C6/'Historical FS'!C60,0) -> 8.3613381 | D31: =IFERROR('Historical FS'!D6/'Historical FS'!D60,0) -> 7.6867643 | E31: =IFERROR('Historical FS'!E6/'Historical FS'!E60,0) -> 6.9190052 | F31: =IFERROR('Historical FS'!F6/'Historical FS'!F60,0) -> 7.7392856 | G31: =IFERROR('Historical FS'!G6/'Historical FS'!G60,0) -> 6.9698269 | H31: =IFERROR('Historical FS'!H6/'Historical FS'!H60,0) -> 6.9217099 | I31: =IFERROR('Historical FS'!I6/'Historical FS'!I60,0) -> 7.9015588 | J31: =IFERROR('Historical FS'!J6/'Historical FS'!J60,0) -> 8.4888642 | ... L31: =IFERROR('Historical FS'!L6/'Historical FS'!L60,0) -> 9.3019738 | N31: =IFERROR(AVERAGE(C31:L31),0) -> 7.937244 | O31: =IFERROR(MEDIAN(C31:L31),0) -> 7.8204222
B32: Fixed Asset Turnover | C32: =IFERROR('Historical FS'!C6/'Historical FS'!C53,0) -> 2.5463128 | D32: =IFERROR('Historical FS'!D6/'Historical FS'!D53,0) -> 2.8109343 | E32: =IFERROR('Historical FS'!E6/'Historical FS'!E53,0) -> 2.4012949 | F32: =IFERROR('Historical FS'!F6/'Historical FS'!F53,0) -> 2.714432 | G32: =IFERROR('Historical FS'!G6/'Historical FS'!G53,0) -> 2.0539206 | H32: =IFERROR('Historical FS'!H6/'Historical FS'!H53,0) -> 1.8008727 | I32: =IFERROR('Historical FS'!I6/'Historical FS'!I53,0) -> 2.0053489 | J32: =IFERROR('Historical FS'!J6/'Historical FS'!J53,0) -> 2.6193792 | ... L32: =IFERROR('Historical FS'!L6/'Historical FS'!L53,0) -> 3.800401 | N32: =IFERROR(AVERAGE(C32:L32),0) -> 2.6331377 | O32: =IFERROR(MEDIAN(C32:L32),0) -> 2.582846
B33: Capital Turnover | C33: =IFERROR('Historical FS'!C6/SUM('Historical FS'!C47:C48),0) -> 3.4583567 | D33: =IFERROR('Historical FS'!D6/SUM('Historical FS'!D47:D48),0) -> 4.6449144 | E33: =IFERROR('Historical FS'!E6/SUM('Historical FS'!E47:E48),0) -> 3.0551909 | F33: =IFERROR('Historical FS'!F6/SUM('Historical FS'!F47:F48),0) -> 5.0172916 | G33: =IFERROR('Historical FS'!G6/SUM('Historical FS'!G47:G48),0) -> 4.138777 | H33: =IFERROR('Historical FS'!H6/SUM('Historical FS'!H47:H48),0) -> 4.5214404 | I33: =IFERROR('Historical FS'!I6/SUM('Historical FS'!I47:I48),0) -> 6.2487853 | J33: =IFERROR('Historical FS'!J6/SUM('Historical FS'!J47:J48),0) -> 7.6335681 | ... L33: =IFERROR('Historical FS'!L6/SUM('Historical FS'!L47:L48),0) -> 3.7857746 | N33: =IFERROR(AVERAGE(C33:L33),0) -> 4.76151 | O33: =IFERROR(MEDIAN(C33:L33),0) -> 4.5831774
B35: Debtor Days | C35: =IFERROR(365/C29,0) -> 18.141227 | D35: =IFERROR(365/D29,0) -> 19.049753 | E35: =IFERROR(365/E29,0) -> 24.904965 | F35: =IFERROR(365/F29,0) -> 22.963631 | G35: =IFERROR(365/G29,0) -> 15.620575 | H35: =IFERROR(365/H29,0) -> 18.526667 | I35: =IFERROR(365/I29,0) -> 16.309265 | J35: =IFERROR(365/J29,0) -> 16.603779 | ... L35: =IFERROR(365/L29,0) -> 10.997441 | N35: =IFERROR(AVERAGE(C35:L35),0) -> 17.737364 | O35: =IFERROR(MEDIAN(C35:L35),0) -> 17.372503
B36: Payable Days | C36: =IFERROR(365/C30,0) -> 153.55746 | D36: =IFERROR(365/D30,0) -> 183.94574 | E36: =IFERROR(365/E30,0) -> 178.79203 | F36: =IFERROR(365/F30,0) -> 168.45236 | G36: =IFERROR(365/G30,0) -> 184.98755 | H36: =IFERROR(365/H30,0) -> 210.69421 | I36: =IFERROR(365/I30,0) -> 180.95902 | J36: =IFERROR(365/J30,0) -> 163.77953 | ... L36: =IFERROR(365/L30,0) -> 157.13275 | N36: =IFERROR(AVERAGE(C36:L36),0) -> 173.14397 | O36: =IFERROR(MEDIAN(C36:L36),0) -> 173.62219
B37: Inventory Days | C37: =IFERROR(365/C31,0) -> 43.6533 | D37: =IFERROR(365/D31,0) -> 47.484219 | E37: =IFERROR(365/E31,0) -> 52.753249 | F37: =IFERROR(365/F31,0) -> 47.161976 | G37: =IFERROR(365/G31,0) -> 52.368589 | H37: =IFERROR(365/H31,0) -> 52.732635 | I37: =IFERROR(365/I31,0) -> 46.193417 | J37: =IFERROR(365/J31,0) -> 42.997507 | ... L37: =IFERROR(365/L31,0) -> 39.238984 | N37: =IFERROR(AVERAGE(C37:L37),0) -> 46.477276 | O37: =IFERROR(MEDIAN(C37:L37),0) -> 46.677696
B38: Cash Conversion Cycle | C38: =IFERROR(C35+C37-C36,0) -> -91.762933 | D38: =IFERROR(D35+D37-D36,0) -> -117.41177 | E38: =IFERROR(E35+E37-E36,0) -> -101.13382 | F38: =IFERROR(F35+F37-F36,0) -> -98.326751 | G38: =IFERROR(G35+G37-G36,0) -> -116.99839 | H38: =IFERROR(H35+H37-H36,0) -> -139.4349 | I38: =IFERROR(I35+I37-I36,0) -> -118.45634 | J38: =IFERROR(J35+J37-J36,0) -> -104.17824 | ... L38: =IFERROR(L35+L37-L36,0) -> -106.89633 | N38: =IFERROR(AVERAGE(C38:L38),0) -> -108.92933 | O38: =IFERROR(MEDIAN(C38:L38),0) -> -105.53729
B40: CFO/Sales | C40: =IFERROR('Historical FS'!C78/'Historical FS'!C6,0) -> 0.14360971 | D40: =IFERROR('Historical FS'!D78/'Historical FS'!D6,0) -> 0.12404497 | E40: =IFERROR('Historical FS'!E78/'Historical FS'!E6,0) -> 0.059759806 | F40: =IFERROR('Historical FS'!F78/'Historical FS'!F6,0) -> 0.03865358 | G40: =IFERROR('Historical FS'!G78/'Historical FS'!G6,0) -> 0.12141666 | H40: =IFERROR('Historical FS'!H78/'Historical FS'!H6,0) -> 0.11572301 | I40: =IFERROR('Historical FS'!I78/'Historical FS'!I6,0) -> 0.012684339 | J40: =IFERROR('Historical FS'!J78/'Historical FS'!J6,0) -> 0.093248786 | ... L40: =IFERROR('Historical FS'!L78/'Historical FS'!L6,0) -> 0.16206234 | N40: =IFERROR(AVERAGE(C40:L40),0) -> 0.10445609 | O40: =IFERROR(MEDIAN(C40:L40),0) -> 0.11856983
B41: CFO/Total Assets | C41: =IFERROR('Historical FS'!C78/'Historical FS'!C62,0) -> 0.51132499 | D41: =IFERROR('Historical FS'!D78/'Historical FS'!D62,0) -> 0.39247413 | E41: =IFERROR('Historical FS'!E78/'Historical FS'!E62,0) -> 0.18027864 | F41: =IFERROR('Historical FS'!F78/'Historical FS'!F62,0) -> 0.12873555 | G41: =IFERROR('Historical FS'!G78/'Historical FS'!G62,0) -> 0.38488747 | H41: =IFERROR('Historical FS'!H78/'Historical FS'!H62,0) -> 0.30250063 | I41: =IFERROR('Historical FS'!I78/'Historical FS'!I62,0) -> 0.039976616 | J41: =IFERROR('Historical FS'!J78/'Historical FS'!J62,0) -> 0.34500452 | ... L41: =IFERROR('Historical FS'!L78/'Historical FS'!L62,0) -> 0.70308137 | N41: =IFERROR(AVERAGE(C41:L41),0) -> 0.36688794 | O41: =IFERROR(MEDIAN(C41:L41),0) -> 0.36494599
B42: Cfo/Total Debt | C42: =IFERROR('Historical FS'!C78/'Historical FS'!C49,0) -> 0.56534058 | D42: =IFERROR('Historical FS'!D78/'Historical FS'!D49,0) -> 0.42560186 | E42: =IFERROR('Historical FS'!E78/'Historical FS'!E49,0) -> 0.19587305 | F42: =IFERROR('Historical FS'!F78/'Historical FS'!F49,0) -> 0.10992195 | G42: =IFERROR('Historical FS'!G78/'Historical FS'!G49,0) -> 0.25401554 | H42: =IFERROR('Historical FS'!H78/'Historical FS'!H49,0) -> 0.20338341 | I42: =IFERROR('Historical FS'!I78/'Historical FS'!I49,0) -> 0.024117606 | J42: =IFERROR('Historical FS'!J78/'Historical FS'!J49,0) -> 0.24055009 | ... L42: =IFERROR('Historical FS'!L78/'Historical FS'!L49,0) -> 0.99605815 | N42: =IFERROR(AVERAGE(C42:L42),0) -> 0.37163091 | O42: =IFERROR(MEDIAN(C42:L42),0) -> 0.24728282
B44: RETURN ON ASSETS
B45: PAT vs Total Assets | C45: =IFERROR('Historical FS'!C33/'Historical FS'!C64,0) -> 0.052322078 | D45: =IFERROR('Historical FS'!D33/'Historical FS'!D64,0) -> 0.015387976 | E45: =IFERROR('Historical FS'!E33/'Historical FS'!E64,0) -> 0.0026906847 | F45: =IFERROR('Historical FS'!F33/'Historical FS'!F64,0) -> -0.0073517316 | G45: =IFERROR('Historical FS'!G33/'Historical FS'!G64,0) -> -0.034596043 | H45: =IFERROR('Historical FS'!H33/'Historical FS'!H64,0) -> -0.0055576031 | I45: =IFERROR('Historical FS'!I33/'Historical FS'!I64,0) -> -0.0415082 | J45: =IFERROR('Historical FS'!J33/'Historical FS'!J64,0) -> -0.011874525 | ... L45: =IFERROR('Historical FS'!L33/'Historical FS'!L64,0) -> 0.043438124 | N45: =IFERROR(AVERAGE(C45:L45),0) -> 0.0086058919 | O45: =IFERROR(MEDIAN(C45:L45),0) -> -0.0014334592
B46: EBIT vs Total Assets | C46: =IFERROR(('Historical FS'!C18-'Historical FS'!C24)/'Historical FS'!C64,0) -> 0.082392775 | D46: =IFERROR(('Historical FS'!D18-'Historical FS'!D24)/'Historical FS'!D64,0) -> 0.042863323 | E46: =IFERROR(('Historical FS'!E18-'Historical FS'!E24)/'Historical FS'!E64,0) -> 0.030269981 | F46: =IFERROR(('Historical FS'!F18-'Historical FS'!F24)/'Historical FS'!F64,0) -> 0.0035122268 | G46: =IFERROR(('Historical FS'!G18-'Historical FS'!G24)/'Historical FS'!G64,0) -> -0.010738855 | H46: =IFERROR(('Historical FS'!H18-'Historical FS'!H24)/'Historical FS'!H64,0) -> 0.025589842 | I46: =IFERROR(('Historical FS'!I18-'Historical FS'!I24)/'Historical FS'!I64,0) -> -0.00035130212 | J46: =IFERROR(('Historical FS'!J18-'Historical FS'!J24)/'Historical FS'!J64,0) -> 0.020782705 | ... L46: =IFERROR(('Historical FS'!L18-'Historical FS'!L24)/'Historical FS'!L64,0) -> 0.084780608 | N46: =IFERROR(AVERAGE(C46:L46),0) -> 0.036187062 | O46: =IFERROR(MEDIAN(C46:L46),0) -> 0.027929912
B47: PAT after Tax benefit vs Total Assets | C47: =(('Historical FS'!C18-'Historical FS'!C24)-('Historical FS'!C21-('Historical FS'!C21*'Historical FS'!C31)))/'Historical FS'!C64 -> 0.067161999 | D47: =(('Historical FS'!D18-'Historical FS'!D24)-('Historical FS'!D21-('Historical FS'!D21*'Historical FS'!D31)))/'Historical FS'!D64 -> 0.034104646 | E47: =(('Historical FS'!E18-'Historical FS'!E24)-('Historical FS'!E21-('Historical FS'!E21*'Historical FS'!E31)))/'Historical FS'!E64 -> 0.027857784 | F47: =(('Historical FS'!F18-'Historical FS'!F24)-('Historical FS'!F21-('Historical FS'!F21*'Historical FS'!F31)))/'Historical FS'!F64 -> -0.0055243975 | G47: =(('Historical FS'!G18-'Historical FS'!G24)-('Historical FS'!G21-('Historical FS'!G21*'Historical FS'!G31)))/'Historical FS'!G64 -> -0.034198678 | H47: =(('Historical FS'!H18-'Historical FS'!H24)-('Historical FS'!H21-('Historical FS'!H21*'Historical FS'!H31)))/'Historical FS'!H64 -> 0.095515811 | I47: =(('Historical FS'!I18-'Historical FS'!I24)-('Historical FS'!I21-('Historical FS'!I21*'Historical FS'!I31)))/'Historical FS'!I64 -> -0.041350526 | J47: =(('Historical FS'!J18-'Historical FS'!J24)-('Historical FS'!J21-('Historical FS'!J21*'Historical FS'!J31)))/'Historical FS'!J64 -> -0.016349171 | ... L47: =(('Historical FS'!L18-'Historical FS'!L24)-('Historical FS'!L21-('Historical FS'!L21*'Historical FS'!L31)))/'Historical FS'!L64 -> 0.076565554 | N47: =IFERROR(AVERAGE(C47:L47),0) -> 0.026240448 | O47: =IFERROR(MEDIAN(C47:L47),0) -> 0.030981215
B49: RETURN ON EQUITY
B50: EPS | C50: =IFERROR('Historical FS'!C38,0) -> 47.694444 | D50: =IFERROR('Historical FS'!D38,0) -> 14.527275 | E50: =IFERROR('Historical FS'!E38,0) -> 3.0491116 | F50: =IFERROR('Historical FS'!F38,0) -> -7.7839158 | G50: =IFERROR('Historical FS'!G38,0) -> -35.859307 | H50: =IFERROR('Historical FS'!H38,0) -> -5.7172846 | I50: =IFERROR('Historical FS'!I38,0) -> -41.132141 | J50: =IFERROR('Historical FS'!J38,0) -> -11.965495 | ... L50: =IFERROR('Historical FS'!L38,0) -> 44.481569 | N50: =IFERROR(AVERAGE(C50:L50),0) -> 8.8574155 | O50: =IFERROR(MEDIAN(C50:L50),0) -> -1.3340865
B51: Cash Flow Earning Per Share | C51: =IFERROR(('Historical FS'!C33+'Historical FS'!C24)/'Historical FS'!C36,0) -> 105.57329 | D51: =IFERROR(('Historical FS'!D33+'Historical FS'!D24)/'Historical FS'!D36,0) -> 76.540193 | E51: =IFERROR(('Historical FS'!E33+'Historical FS'!E24)/'Historical FS'!E36,0) -> 77.69875 | F51: =IFERROR(('Historical FS'!F33+'Historical FS'!F24)/'Historical FS'!F36,0) -> 73.920895 | G51: =IFERROR(('Historical FS'!G33+'Historical FS'!G24)/'Historical FS'!G36,0) -> 33.501101 | H51: =IFERROR(('Historical FS'!H33+'Historical FS'!H24)/'Historical FS'!H36,0) -> 65.200133 | I51: =IFERROR(('Historical FS'!I33+'Historical FS'!I24)/'Historical FS'!I36,0) -> 33.658385 | J51: =IFERROR(('Historical FS'!J33+'Historical FS'!J24)/'Historical FS'!J36,0) -> 62.885798 | ... L51: =IFERROR(('Historical FS'!L33+'Historical FS'!L24)/'Historical FS'!L36,0) -> 107.6549 | N51: =IFERROR(AVERAGE(C51:L51),0) -> 79.986719 | O51: =IFERROR(MEDIAN(C51:L51),0) -> 75.230544
B52: Dividend Per Share | C52: =IFERROR('Historical FS'!C41,0) -> 67.92 | D52: =IFERROR('Historical FS'!D41,0) -> 0 | E52: =IFERROR('Historical FS'!E41,0) -> 0 | F52: =IFERROR('Historical FS'!F41,0) -> 0 | G52: =IFERROR('Historical FS'!G41,0) -> 0 | H52: =IFERROR('Historical FS'!H41,0) -> 0 | I52: =IFERROR('Historical FS'!I41,0) -> 0 | J52: =IFERROR('Historical FS'!J41,0) -> 766.02 | ... L52: =IFERROR('Historical FS'!L41,0) -> 2208 | N52: =IFERROR(AVERAGE(C52:L52),0) -> 534.294 | O52: =IFERROR(MEDIAN(C52:L52),0) -> 0
B53: Dividend Pay Out Ratio | C53: =IFERROR('Historical FS'!C42,0) -> 0.23524522 | D53: =IFERROR('Historical FS'!D42,0) -> 0 | E53: =IFERROR('Historical FS'!E42,0) -> 0 | F53: =IFERROR('Historical FS'!F42,0) -> 0 | G53: =IFERROR('Historical FS'!G42,0) -> 0 | H53: =IFERROR('Historical FS'!H42,0) -> 0 | I53: =IFERROR('Historical FS'!I42,0) -> 0 | J53: =IFERROR('Historical FS'!J42,0) -> 2.3063861 | ... L53: =IFERROR('Historical FS'!L42,0) -> 5.9978812 | N53: =IFERROR(AVERAGE(C53:L53),0) -> 1.546252 | O53: =IFERROR(MEDIAN(C53:L53),0) -> 0
B54: Dividend Yield Ratio | C54: =IFERROR(C53/'Data Sheet'!B8,0) -> 0.00034167788 | D54: =IFERROR(D53/'Data Sheet'!C8,0) -> 0 | E54: =IFERROR(E53/'Data Sheet'!D8,0) -> 0 | F54: =IFERROR(F53/'Data Sheet'!E8,0) -> 0 | G54: =IFERROR(G53/'Data Sheet'!F8,0) -> 0 | H54: =IFERROR(H53/'Data Sheet'!G8,0) -> 0 | I54: =IFERROR(I53/'Data Sheet'!H8,0) -> 0 | J54: =IFERROR(J53/'Data Sheet'!I8,0) -> 0 | ... L54: =IFERROR(L53/'Data Sheet'!K8,0) -> 0

Sheet Forecasting
B3: ='Data Sheet'!$B$1&" - "&'Data Sheet'!$A$17& " Forecasting" -> TATA MOTORS LTD - Sales Forecasting | G3: ='Data Sheet'!$B$1&" - "&'Historical FS'!B18 & " Forecasting" -> TATA MOTORS LTD - EBITDA Forecasting
B4: Year Weight | C4: Year | D4: Sales | E4: Sales Growth | G4: Year Weight | H4: Year | I4: Sales | J4: Sales Growth
B5: 1 | C5: 2014 | D5: 232834 | E5: - | G5: 1 | H5: 2014 | I5: - | J5: -
B6: 2 | C6: 2015 | D6: 263159 | E6: =D6/D5-1 -> 0.13024301 | G6: 2 | H6: 2015 | I6: - | J6: -
B7: 3 | C7: 2016 | D7: 273046 | E7: =D7/D6-1 -> 0.037570442 | G7: 3 | H7: 2016 | I7: {=TRANSPOSE('Historical FS'!C18:M18)} -> 38395.25 | J7: -
B8: 4 | C8: 2017 | D8: 269693 | E8: =D8/D7-1 -> -0.012279982 | G8: 4 | H8: 2017 | I8: 29588.69 | J8: =I8/I7-1 -> -0.22936587
B9: 5 | C9: 2018 | D9: 291550 | E9: =D9/D8-1 -> 0.081044002 | G9: 5 | H9: 2018 | I9: 31457.68 | J9: =I9/I8-1 -> 0.063165689
B10: 6 | C10: 2019 | D10: 301938 | E10: =D10/D9-1 -> 0.035630252 | G10: 6 | H10: 2019 | I10: 24664.33 | J10: =I10/I9-1 -> -0.21595203
B11: 7 | C11: 2020 | D11: 261068 | E11: =D11/D10-1 -> -0.13535891 | G11: 7 | H11: 2020 | I11: 17987.07 | J11: =I11/I10-1 -> -0.27072538
B12: 8 | C12: 2021 | D12: 249795 | E12: =D12/D11-1 -> -0.043180321 | G12: 8 | H12: 2021 | I12: 32287.43 | J12: =I12/I11-1 -> 0.79503554
B13: 9 | C13: 2022 | D13: 278454 | E13: =D13/D12-1 -> 0.11473008 | G13: 9 | H13: 2022 | I13: 24720.09 | J13: =I13/I12-1 -> -0.23437418
B14: 10 | C14: 2023 | D14: 345967 | E14: =D14/D13-1 -> 0.24245656 | G14: 10 | H14: 2023 | I14: 31815.8 | J14: =I14/I13-1 -> 0.28704224
B15: 11 | C15: 2024 | D15: 434016 | E15: =D15/D14-1 -> 0.25450115 | G15: 11 | H15: 2024 | I15: 57824 | J15: =I15/I14-1 -> 0.81746176
B16: 12 | C16: 2025 | D16: 439695 | E16: =D16/D15-1 -> 0.013084771 | G16: 12 | H16: 2025 | I16: 55216 | J16: =I16/I15-1 -> -0.04510238
B17: 13 | C17: 2026 | D17: =FORECAST(B17,$D$5:$D$16,$B$5:$B$16) -> 398918.7 | E17: =D17/D16-1 -> -0.0927377 | G17: 13 | H17: 2026 | I17: =FORECAST(G17,I7:I16,G7:G16) -> 46572.039 | J17: =I17/I16-1 -> -0.15654811
B18: 14 | C18: 2027 | D18: =FORECAST(B18,$D$5:$D$16,$B$5:$B$16) -> 413608.56 | E18: =D18/D17-1 -> 0.036824204 | G18: 14 | H18: 2027 | I18: =FORECAST(G18,I8:I17,G8:G17) -> 52509.166 | J18: =I18/I17-1 -> 0.12748264
B19: 15 | C19: 2028 | D19: =FORECAST(B19,$D$5:$D$16,$B$5:$B$16) -> 428298.42 | E19: =D19/D18-1 -> 0.035516343 | G19: 15 | H19: 2028 | I19: =FORECAST(G19,I9:I18,G9:G18) -> 57927.607 | J19: =I19/I18-1 -> 0.1031904

Sheet Data>

Sheet CFS
C2: 41699 | D2: 42064 | E2: 42430 | F2: 42795 | G2: 43160 | H2: 43525 | I2: 43891 | J2: 44256 | K2: 44621 | L2: 44986 | M2: 45352 | N2: 45717
B3: Cash from Operating Activity - | C3: 36151 | D3: 35531 | E3: 37900 | F3: 30199 | G3: 23857 | H3: 18891 | I3: 26633 | J3: 29001 | K3: 14283 | L3: 35388 | M3: 67915 | N3: 63102
B4: Profit from operations | C4: 36303 | D4: 43397 | E4: 38626 | F4: 28840 | G4: 33312 | H4: 28771 | I4: 23352 | J4: 31198 | K4: 26943 | L4: 41694 | M4: 65106 | N4: 58937
B5: Receivables | C5: 445 | D5: -3179 | E5: -2223 | F5: -4152 | G5: -10688 | H5: -9109 | I5: 9950 | J5: -5505 | K5: 185 | L5: -2213 | M5: -1876 | N5: 3573
B6: Inventory | C6: -2853 | D6: -3692 | E6: -5743 | F6: -6621 | G6: -3560 | H6: 2069 | I6: 2326 | J6: 3814 | K6: 472 | L6: -5665 | M6: -7265 | N6: 2127
B7: Payables | C7: 4694 | D7: 3598 | E7: 3947 | F7: 9301 | G7: 7320 | H7: -4692 | I7: -8085 | J7: 5748 | K7: -7012 | L7: 6945 | M7: 13706 | N7: 1303
B8: Loans Advances | C8: 0 | D8: 0 | E8: -520 | F8: 0 | G8: 0 | H8: 0 | I8: 0 | J8: 0 | K8: 0 | L8: 0 | M8: 0 | N8: 0
B9: Other WC items | C9: 1870 | D9: -398 | E9: 5852 | F9: 4727 | G9: 494 | H9: 4512 | I9: 875 | J9: -4150 | K9: -4396 | L9: -2194 | M9: 2760 | N9: 1153
B10: Working capital changes | C10: 4157 | D10: -3672 | E10: 1313 | F10: 3254 | G10: -6434 | H10: -7221 | I10: 5065 | J10: -93 | K10: -10750 | L10: -3127 | M10: 7325 | N10: 8156
B11: Direct taxes | C11: -4308 | D11: -4194 | E11: -2040 | F11: -1895 | G11: -3021 | H11: -2659 | I11: -1785 | J11: -2105 | K11: -1910 | L11: -3179 | M11: -4516 | N11: -3991
B12: Cash from Investing Activity - | C12: -27991 | D12: -36232 | E12: -36694 | F12: -39571 | G12: -25139 | H12: -20878 | I12: -33115 | J12: -25672 | K12: -4444 | L12: -15417 | M12: -22781 | N12: -49982
B13: Fixed assets purchased | C13: -26975 | D13: -31962 | E13: -31503 | F13: -16072 | G13: -35079 | H13: -35304 | I13: -29702 | J13: -20205 | K13: -15168 | L13: -19230 | M13: -31414 | N13: -38042
B14: Fixed assets sold | C14: 50 | D14: 74 | E14: 59 | F14: 53 | G14: 30 | H14: 67 | I14: 171 | J14: 351 | K14: 230 | L14: 285 | M14: 231 | N14: 974
... B33: Net Cash Flow | C33: 4277 | D33: 4500 | E33: -2589 | F33: -3167 | G33: 730 | H33: 6843 | I33: -3092 | J33: 13232 | K33: 6459 | L33: -6272 | M33: 8128 | N33: -5666

Sheet Profit & Loss
A1: ='Data Sheet'!B1 -> TATA MOTORS LTD | H1: =UPDATE | M1: SCREENER.IN
A3: Narration | B3: ='Data Sheet'!B16 -> 42460 | C3: ='Data Sheet'!C16 -> 42825 | D3: ='Data Sheet'!D16 -> 43190 | E3: ='Data Sheet'!E16 -> 43555 | F3: ='Data Sheet'!F16 -> 43921 | G3: ='Data Sheet'!G16 -> 44286 | H3: ='Data Sheet'!H16 -> 44651 | I3: ='Data Sheet'!I16 -> 45016 | ... K3: ='Data Sheet'!K16 -> 45747 | L3: Trailing | M3: Best Case | N3: Worst Case
A4: Sales | B4: ='Data Sheet'!B17 -> 273045.6 | C4: ='Data Sheet'!C17 -> 269692.51 | D4: ='Data Sheet'!D17 -> 291550.48 | E4: ='Data Sheet'!E17 -> 301938.4 | F4: ='Data Sheet'!F17 -> 261067.97 | G4: ='Data Sheet'!G17 -> 249794.75 | H4: ='Data Sheet'!H17 -> 278453.62 | I4: ='Data Sheet'!I17 -> 345966.97 | ... K4: ='Data Sheet'!K17 -> 439695 | L4: =SUM(Quarters!H4:K4) -> 441609 | M4: =$K4+M23*K4 -> 512017.04 | N4: =$K4+N23*L4 -> 445473.35
A5: Expenses | B5: =SUM('Data Sheet'!B18,'Data Sheet'!B20:B24, -1*'Data Sheet'!B19) -> 234650.35 | C5: =SUM('Data Sheet'!C18,'Data Sheet'!C20:C24, -1*'Data Sheet'!C19) -> 240103.82 | D5: =SUM('Data Sheet'!D18,'Data Sheet'!D20:D24, -1*'Data Sheet'!D19) -> 260092.8 | E5: =SUM('Data Sheet'!E18,'Data Sheet'!E20:E24, -1*'Data Sheet'!E19) -> 277274.07 | F5: =SUM('Data Sheet'!F18,'Data Sheet'!F20:F24, -1*'Data Sheet'!F19) -> 243080.9 | G5: =SUM('Data Sheet'!G18,'Data Sheet'!G20:G24, -1*'Data Sheet'!G19) -> 217507.32 | H5: =SUM('Data Sheet'!H18,'Data Sheet'!H20:H24, -1*'Data Sheet'!H19) -> 253733.53 | I5: =SUM('Data Sheet'!I18,'Data Sheet'!I20:I24, -1*'Data Sheet'!I19) -> 314151.17 | ... K5: =SUM('Data Sheet'!K18,'Data Sheet'!K20:K24, -1*'Data Sheet'!K19) -> 384479 | L5: =SUM(Quarters!H5:K5) -> 384424 | M5: =M4-M6 -> 445714.73 | N5: =N4-N6 -> 398338.79
A6: Operating Profit | B6: =B4-B5 -> 38395.25 | C6: =C4-C5 -> 29588.69 | D6: =D4-D5 -> 31457.68 | E6: =E4-E5 -> 24664.33 | F6: =F4-F5 -> 17987.07 | G6: =G4-G5 -> 32287.43 | H6: =H4-H5 -> 24720.09 | I6: =I4-I5 -> 31815.8 | ... K6: =K4-K5 -> 55216 | L6: =SUM(Quarters!H6:K6) -> 57185 | M6: =M4*M24 -> 66302.304 | N6: =N4*N24 -> 47134.558
A7: Other Income | B7: ='Data Sheet'!B25 -> -2669.62 | C7: ='Data Sheet'!C25 -> 1869.1 | D7: ='Data Sheet'!D25 -> 5932.73 | E7: ='Data Sheet'!E25 -> -26686.25 | F7: ='Data Sheet'!F25 -> 101.71 | G7: ='Data Sheet'!G25 -> -11117.83 | H7: ='Data Sheet'!H25 -> 2424.05 | I7: ='Data Sheet'!I25 -> 6663.97 | ... K7: ='Data Sheet'!K25 -> 11774 | L7: =SUM(Quarters!H7:K7) -> 6151 | M7: 0 | N7: 0
A8: Depreciation | B8: ='Data Sheet'!B26 -> 16710.78 | C8: ='Data Sheet'!C26 -> 17904.99 | D8: ='Data Sheet'!D26 -> 21553.59 | E8: ='Data Sheet'!E26 -> 23590.63 | F8: ='Data Sheet'!F26 -> 21425.43 | G8: ='Data Sheet'!G26 -> 23546.71 | H8: ='Data Sheet'!H26 -> 24835.69 | I8: ='Data Sheet'!I26 -> 24860.36 | ... K8: ='Data Sheet'!K26 -> 23256 | L8: =SUM(Quarters!H8:K8) -> 23273 | M8: =+$L8 -> 23273 | N8: =+$L8 -> 23273
A9: Interest | B9: ='Data Sheet'!B27 -> 4889.08 | C9: ='Data Sheet'!C27 -> 4238.01 | D9: ='Data Sheet'!D27 -> 4681.79 | E9: ='Data Sheet'!E27 -> 5758.6 | F9: ='Data Sheet'!F27 -> 7243.33 | G9: ='Data Sheet'!G27 -> 8097.17 | H9: ='Data Sheet'!H27 -> 9311.86 | I9: ='Data Sheet'!I27 -> 10225.48 | ... K9: ='Data Sheet'!K27 -> 5083 | L9: =SUM(Quarters!H9:K9) -> 6317 | M9: =+$L9 -> 6317 | N9: =+$L9 -> 6317
A10: Profit before tax | B10: ='Data Sheet'!B28 -> 14125.77 | C10: ='Data Sheet'!C28 -> 9314.79 | D10: ='Data Sheet'!D28 -> 11155.03 | E10: ='Data Sheet'!E28 -> -31371.15 | F10: ='Data Sheet'!F28 -> -10579.98 | G10: ='Data Sheet'!G28 -> -10474.28 | H10: ='Data Sheet'!H28 -> -7003.41 | I10: ='Data Sheet'!I28 -> 3393.93 | ... K10: ='Data Sheet'!K28 -> 38651 | L10: =SUM(Quarters!H10:K10) -> 33746 | M10: =M6+M7-SUM(M8:M9) -> 36712.304 | N10: =N6+N7-SUM(N8:N9) -> 17544.558
A11: Tax | B11: ='Data Sheet'!B29 -> 3025.05 | C11: ='Data Sheet'!C29 -> 3251.23 | D11: ='Data Sheet'!D29 -> 4341.93 | E11: ='Data Sheet'!E29 -> -2437.45 | F11: ='Data Sheet'!F29 -> 395.25 | G11: ='Data Sheet'!G29 -> 2541.86 | H11: ='Data Sheet'!H29 -> 4231.29 | I11: ='Data Sheet'!I29 -> 704.06 | ... K11: ='Data Sheet'!K29 -> 10502 | L11: =SUM(Quarters!H11:K11) -> 10563 | M11: =IF($L10>0,$L11/$L10,0) -> 0.31301488 | N11: =IF($L10>0,$L11/$L10,0) -> 0.31301488
A12: Net profit | B12: ='Data Sheet'!B30 -> 11579.31 | C12: ='Data Sheet'!C30 -> 7454.36 | D12: ='Data Sheet'!D30 -> 8988.91 | E12: ='Data Sheet'!E30 -> -28826.23 | F12: ='Data Sheet'!F30 -> -12070.85 | G12: ='Data Sheet'!G30 -> -13451.39 | H12: ='Data Sheet'!H30 -> -11441.47 | I12: ='Data Sheet'!I30 -> 2414.29 | ... K12: ='Data Sheet'!K30 -> 27830 | L12: =SUM(Quarters!H12:K12) -> 22785 | M12: =M10-M11*M10 -> 25220.807 | N12: =N10-N11*N10 -> 12052.85
A13: EPS | B13: =IF('Data Sheet'!B93>0,B12/'Data Sheet'!B93,0) -> 40.105673 | C13: =IF('Data Sheet'!C93>0,C12/'Data Sheet'!C93,0) -> 25.817754 | D13: =IF('Data Sheet'!D93>0,D12/'Data Sheet'!D93,0) -> 31.132581 | E13: =IF('Data Sheet'!E93>0,E12/'Data Sheet'!E93,0) -> -99.838015 | F13: =IF('Data Sheet'!F93>0,F12/'Data Sheet'!F93,0) -> -39.076886 | G13: =IF('Data Sheet'!G93>0,G12/'Data Sheet'!G93,0) -> -40.512574 | H13: =IF('Data Sheet'!H93>0,H12/'Data Sheet'!H93,0) -> -34.454994 | I13: =IF('Data Sheet'!I93>0,I12/'Data Sheet'!I93,0) -> 7.2691115 | ... K13: =IF('Data Sheet'!K93>0,K12/'Data Sheet'!K93,0) -> 75.598294 | L13: =IF('Data Sheet'!$B6>0,'Profit & Loss'!L12/'Data Sheet'!$B6,0) -> 61.89118 | M13: =IF('Data Sheet'!$B6>0,'Profit & Loss'!M12/'Data Sheet'!$B6,0) -> 68.507593 | N13: =IF('Data Sheet'!$B6>0,'Profit & Loss'!N12/'Data Sheet'!$B6,0) -> 32.739308
A14: Price to earning | B14: =IF(B15>0,B15/B13,"") -> 9.639534 | C14: =IF(C15>0,C15/C13,"") -> 18.043785 | D14: =IF(D15>0,D15/D13,"") -> 10.498648 | E14: =IF(E15>0,E15/E13,"") -> -1.7453272 | F14: =IF(F15>0,F15/F13,"") -> -1.8182104 | G14: =IF(G15>0,G15/G13,"") -> -7.449539 | H14: =IF(H15>0,H15/H13,"") -> -12.588886 | I14: =IF(I15>0,I15/I13,"") -> 57.888781 | ... K14: =IF(K15>0,K15/K13,"") -> 8.9214976 | L14: =IF(L13>0,L15/L13,0) -> 11.124364 | M14: =M25 -> 22.110949 | N14: =N25 -> 11.124364
A15: Price | B15: ='Data Sheet'!B90 -> 386.6 | C15: ='Data Sheet'!C90 -> 465.85 | D15: ='Data Sheet'!D90 -> 326.85 | E15: ='Data Sheet'!E90 -> 174.25 | F15: ='Data Sheet'!F90 -> 71.05 | G15: ='Data Sheet'!G90 -> 301.8 | H15: ='Data Sheet'!H90 -> 433.75 | I15: ='Data Sheet'!I90 -> 420.8 | ... K15: ='Data Sheet'!K90 -> 674.45 | L15: ='Data Sheet'!B8 -> 688.5 | M15: =M13*M14 -> 1514.7679 | N15: =N13*N14 -> 364.20397
A17: RATIOS:
A18: Dividend Payout | B18: =IF('Data Sheet'!B30>0, 'Data Sheet'!B31/'Data Sheet'!B30, 0) -> 0.0058656345 | C18: =IF('Data Sheet'!C30>0, 'Data Sheet'!C31/'Data Sheet'!C30, 0) -> 0 | D18: =IF('Data Sheet'!D30>0, 'Data Sheet'!D31/'Data Sheet'!D30, 0) -> 0 | E18: =IF('Data Sheet'!E30>0, 'Data Sheet'!E31/'Data Sheet'!E30, 0) -> 0 | F18: =IF('Data Sheet'!F30>0, 'Data Sheet'!F31/'Data Sheet'!F30, 0) -> 0 | G18: =IF('Data Sheet'!G30>0, 'Data Sheet'!G31/'Data Sheet'!G30, 0) -> 0 | H18: =IF('Data Sheet'!H30>0, 'Data Sheet'!H31/'Data Sheet'!H30, 0) -> 0 | I18: =IF('Data Sheet'!I30>0, 'Data Sheet'!I31/'Data Sheet'!I30, 0) -> 0.31728583 | ... K18: =IF('Data Sheet'!K30>0, 'Data Sheet'!K31/'Data Sheet'!K30, 0) -> 0.079338843
A19: OPM | B19: =IF(B6>0,B6/B4,0) -> 0.14061845 | C19: =IF(C6>0,C6/C4,0) -> 0.10971269 | D19: =IF(D6>0,D6/D4,0) -> 0.10789788 | E19: =IF(E6>0,E6/E4,0) -> 0.081686629 | F19: =IF(F6>0,F6/F4,0) -> 0.068898034 | G19: =IF(G6>0,G6/G4,0) -> 0.12925584 | H19: =IF(H6>0,H6/H4,0) -> 0.088776328 | I19: =IF(I6>0,I6/I4,0) -> 0.091961958 | ... L19: =IF(L6>0,L6/L4,0) -> 0.12949238
G22: TRENDS: | H22: 10 YEARS | I22: 7 YEARS | J22: 5 YEARS | K22: 3 YEARS | L22: RECENT | M22: BEST | N22: WORST
G23: Sales Growth | H23: =IF(B4=0,"",POWER($K4/B4,1/9)-1) -> 0.05436433 | I23: =IF(D4=0,"",POWER($K4/D4,1/7)-1) -> 0.060452229 | J23: =IF(F4=0,"",POWER($K4/F4,1/5)-1) -> 0.1098891 | K23: =IF(H4=0,"",POWER($K4/H4, 1/3)-1) -> 0.16448229 | L23: =IF(ISERROR(MAX(IF(J4=0,"",(K4-J4)/J4),IF(K4=0,"",(L4-K4)/K4))),"",MAX(IF(J4=0,"",(K4-J4)/J4),IF(K4=0,"",(L4-K4)/K4))) -> 0.013084771 | M23: =MAX(K23:L23) -> 0.16448229 | N23: =MIN(H23:L23) -> 0.013084771
G24: OPM | H24: =IF(SUM(B4:$K$4)=0,"",SUMPRODUCT(B19:$K$19,B4:$K$4)/SUM(B4:$K$4)) -> 0.10935839 | I24: =IF(SUM(E4:$K$4)=0,"",SUMPRODUCT(E19:$K$19,E4:$K$4)/SUM(E4:$K$4)) -> 0.10580781 | J24: =IF(SUM(G4:$K$4)=0,"",SUMPRODUCT(G19:$K$19,G4:$K$4)/SUM(G4:$K$4)) -> 0.11548732 | K24: =IF(SUM(I4:$K$4)=0, "", SUMPRODUCT(I19:$K$19,I4:$K$4)/SUM(I4:$K$4)) -> 0.11876561 | L24: =L19 -> 0.12949238 | M24: =MAX(K24:L24) -> 0.12949238 | N24: =MIN(H24:L24) -> 0.10580781
G25: Price to Earning | H25: =IF(ISERROR(AVERAGEIF(B14:$L14,">0")),"",AVERAGEIF(B14:$L14,">0")) -> 18.089395 | I25: =IF(ISERROR(AVERAGEIF(E14:$L14,">0")),"",AVERAGEIF(E14:$L14,">0")) -> 22.110949 | J25: =IF(ISERROR(AVERAGEIF(G14:$L14,">0")),"",AVERAGEIF(G14:$L14,">0")) -> 22.110949 | K25: =IF(ISERROR(AVERAGEIF(I14:$L14,">0")),"",AVERAGEIF(I14:$L14,">0")) -> 22.110949 | L25: =L14 -> 11.124364 | M25: =MAX(K25:L25) -> 22.110949 | N25: =MIN(H25:L25) -> 11.124364

Sheet Quarters
A1: ='Profit & Loss'!A1 -> TATA MOTORS LTD | E1: =UPDATE | J1: SCREENER.IN
A3: Narration | B3: ='Data Sheet'!B41 -> 44926 | C3: ='Data Sheet'!C41 -> 45016 | D3: ='Data Sheet'!D41 -> 45107 | E3: ='Data Sheet'!E41 -> 45199 | F3: ='Data Sheet'!F41 -> 45291 | G3: ='Data Sheet'!G41 -> 45382 | H3: ='Data Sheet'!H41 -> 45473 | I3: ='Data Sheet'!I41 -> 45565 | ... K3: ='Data Sheet'!K41 -> 45747
A4: Sales | B4: ='Data Sheet'!B42 -> 88488.59 | C4: ='Data Sheet'!C42 -> 105932.35 | D4: ='Data Sheet'!D42 -> 102236 | E4: ='Data Sheet'!E42 -> 105129 | F4: ='Data Sheet'!F42 -> 110577 | G4: ='Data Sheet'!G42 -> 119033 | H4: ='Data Sheet'!H42 -> 108048 | I4: ='Data Sheet'!I42 -> 101450 | ... K4: ='Data Sheet'!K42 -> 119503
A5: Expenses | B5: ='Data Sheet'!B43 -> 77668.35 | C5: ='Data Sheet'!C43 -> 92817.95 | D5: ='Data Sheet'!D43 -> 89019 | E5: ='Data Sheet'!E43 -> 91362 | F5: ='Data Sheet'!F43 -> 95159 | G5: ='Data Sheet'!G43 -> 102348 | H5: ='Data Sheet'!H43 -> 92263 | I5: ='Data Sheet'!I43 -> 89291 | ... K5: ='Data Sheet'!K43 -> 102685
A6: Operating Profit | B6: ='Data Sheet'!B50 -> 10820.24 | C6: ='Data Sheet'!C50 -> 13114.4 | D6: ='Data Sheet'!D50 -> 13217 | E6: ='Data Sheet'!E50 -> 13767 | F6: ='Data Sheet'!F50 -> 15418 | G6: ='Data Sheet'!G50 -> 16685 | H6: ='Data Sheet'!H50 -> 15785 | I6: ='Data Sheet'!I50 -> 12159 | ... K6: ='Data Sheet'!K50 -> 16818
A7: Other Income | B7: ='Data Sheet'!B44 -> 1129.98 | C7: ='Data Sheet'!C44 -> 1452.86 | D7: ='Data Sheet'!D44 -> 895 | E7: ='Data Sheet'!E44 -> 1557 | F7: ='Data Sheet'!F44 -> 1604 | G7: ='Data Sheet'!G44 -> 1412 | H7: ='Data Sheet'!H44 -> 1747 | I7: ='Data Sheet'!I44 -> 1647 | ... K7: ='Data Sheet'!K44 -> 1057
A8: Depreciation | B8: ='Data Sheet'!B45 -> 6071.78 | C8: ='Data Sheet'!C45 -> 7050.2 | D8: ='Data Sheet'!D45 -> 6633 | E8: ='Data Sheet'!E45 -> 6637 | F8: ='Data Sheet'!F45 -> 6850 | G8: ='Data Sheet'!G45 -> 7143 | H8: ='Data Sheet'!H45 -> 6574 | I8: ='Data Sheet'!I45 -> 6005 | ... K8: ='Data Sheet'!K45 -> 5295
A9: Interest | B9: ='Data Sheet'!B46 -> 2675.83 | C9: ='Data Sheet'!C46 -> 2641.67 | D9: ='Data Sheet'!D46 -> 2615 | E9: ='Data Sheet'!E46 -> 2652 | F9: ='Data Sheet'!F46 -> 2485 | G9: ='Data Sheet'!G46 -> 1645 | H9: ='Data Sheet'!H46 -> 2088 | I9: ='Data Sheet'!I46 -> 2034 | ... K9: ='Data Sheet'!K46 -> 1076
A10: Profit before tax | B10: ='Data Sheet'!B47 -> 3202.61 | C10: ='Data Sheet'!C47 -> 4875.39 | D10: ='Data Sheet'!D47 -> 4864 | E10: ='Data Sheet'!E47 -> 6035 | F10: ='Data Sheet'!F47 -> 7687 | G10: ='Data Sheet'!G47 -> 9309 | H10: ='Data Sheet'!H47 -> 8870 | I10: ='Data Sheet'!I47 -> 5767 | ... K10: ='Data Sheet'!K47 -> 11504
A11: Tax | B11: ='Data Sheet'!B48 -> 262.83 | C11: ='Data Sheet'!C48 -> -620.65 | D11: ='Data Sheet'!D48 -> 1563 | E11: ='Data Sheet'!E48 -> 2203 | F11: ='Data Sheet'!F48 -> 542 | G11: ='Data Sheet'!G48 -> -8219 | H11: ='Data Sheet'!H48 -> 3178 | I11: ='Data Sheet'!I48 -> 2317 | ... K11: ='Data Sheet'!K48 -> 2948
A12: Net profit | B12: ='Data Sheet'!B49 -> 2957.71 | C12: ='Data Sheet'!C49 -> 5407.79 | D12: ='Data Sheet'!D49 -> 3203 | E12: ='Data Sheet'!E49 -> 3764 | F12: ='Data Sheet'!F49 -> 7025 | G12: ='Data Sheet'!G49 -> 17407 | H12: ='Data Sheet'!H49 -> 5566 | I12: ='Data Sheet'!I49 -> 3343 | ... K12: ='Data Sheet'!K49 -> 8470
A14: OPM | B14: =IF(B4>0,B6/B4,"") -> 0.12227836 | C14: =IF(C4>0,C6/C4,"") -> 0.12379976 | D14: =IF(D4>0,D6/D4,"") -> 0.12927931 | E14: =IF(E4>0,E6/E4,"") -> 0.1309534 | F14: =IF(F4>0,F6/F4,"") -> 0.13943225 | G14: =IF(G4>0,G6/G4,"") -> 0.14017121 | H14: =IF(H4>0,H6/H4,"") -> 0.14609248 | I14: =IF(I4>0,I6/I4,"") -> 0.11985214 | ... K14: =IF(K4>0,K6/K4,"") -> 0.14073287

Sheet Balance Sheet
A1: ='Profit & Loss'!A1 -> TATA MOTORS LTD | E1: =UPDATE | J1: SCREENER.IN
A3: Narration | B3: ='Data Sheet'!B56 -> 42460 | C3: ='Data Sheet'!C56 -> 42825 | D3: ='Data Sheet'!D56 -> 43190 | E3: ='Data Sheet'!E56 -> 43555 | F3: ='Data Sheet'!F56 -> 43921 | G3: ='Data Sheet'!G56 -> 44286 | H3: ='Data Sheet'!H56 -> 44651 | I3: ='Data Sheet'!I56 -> 45016 | ... K3: ='Data Sheet'!K56 -> 45747
A4: Equity Share Capital | B4: ='Data Sheet'!B57 -> 679.18 | C4: ='Data Sheet'!C57 -> 679.22 | D4: ='Data Sheet'!D57 -> 679.22 | E4: ='Data Sheet'!E57 -> 679.22 | F4: ='Data Sheet'!F57 -> 719.54 | G4: ='Data Sheet'!G57 -> 765.81 | H4: ='Data Sheet'!H57 -> 765.88 | I4: ='Data Sheet'!I57 -> 766.02 | ... K4: ='Data Sheet'!K57 -> 736
A5: Reserves | B5: ='Data Sheet'!B58 -> 78273.23 | C5: ='Data Sheet'!C58 -> 57382.67 | D5: ='Data Sheet'!D58 -> 94748.69 | E5: ='Data Sheet'!E58 -> 59500.34 | F5: ='Data Sheet'!F58 -> 62358.99 | G5: ='Data Sheet'!G58 -> 54480.91 | H5: ='Data Sheet'!H58 -> 43795.36 | I5: ='Data Sheet'!I58 -> 44555.77 | ... K5: ='Data Sheet'!K58 -> 115408
A6: Borrowings | B6: ='Data Sheet'!B59 -> 69359.96 | C6: ='Data Sheet'!C59 -> 78603.98 | D6: ='Data Sheet'!D59 -> 88950.47 | E6: ='Data Sheet'!E59 -> 106175.34 | F6: ='Data Sheet'!F59 -> 124787.64 | G6: ='Data Sheet'!G59 -> 142130.57 | H6: ='Data Sheet'!H59 -> 146449.03 | I6: ='Data Sheet'!I59 -> 134113.44 | ... K6: ='Data Sheet'!K59 -> 71540
A7: Other Liabilities | B7: ='Data Sheet'!B60 -> 114871.75 | C7: ='Data Sheet'!C60 -> 135914.49 | D7: ='Data Sheet'!D60 -> 142813.43 | E7: ='Data Sheet'!E60 -> 139348.59 | F7: ='Data Sheet'!F60 -> 132313.22 | G7: ='Data Sheet'!G60 -> 144192.62 | H7: ='Data Sheet'!H60 -> 138051.22 | I7: ='Data Sheet'!I60 -> 155239.2 | ... K7: ='Data Sheet'!K60 -> 189289
A8: Total | B8: ='Data Sheet'!B61 -> 263184.12 | C8: ='Data Sheet'!C61 -> 272580.36 | D8: ='Data Sheet'!D61 -> 327191.81 | E8: ='Data Sheet'!E61 -> 305703.49 | F8: ='Data Sheet'!F61 -> 320179.39 | G8: ='Data Sheet'!G61 -> 341569.91 | H8: ='Data Sheet'!H61 -> 329061.49 | I8: ='Data Sheet'!I61 -> 334674.43 | ... K8: ='Data Sheet'!K61 -> 376973
A10: Net Block | B10: ='Data Sheet'!B62 -> 107231.76 | C10: ='Data Sheet'!C62 -> 95944.08 | D10: ='Data Sheet'!D62 -> 121413.86 | E10: ='Data Sheet'!E62 -> 111234.47 | F10: ='Data Sheet'!F62 -> 127107.14 | G10: ='Data Sheet'!G62 -> 138707.61 | H10: ='Data Sheet'!H62 -> 138855.45 | I10: ='Data Sheet'!I62 -> 132079.76 | ... K10: ='Data Sheet'!K62 -> 115697
A11: Capital Work in Progress | B11: ='Data Sheet'!B63 -> 25918.94 | C11: ='Data Sheet'!C63 -> 33698.84 | D11: ='Data Sheet'!D63 -> 40033.5 | E11: ='Data Sheet'!E63 -> 31883.84 | F11: ='Data Sheet'!F63 -> 35622.29 | G11: ='Data Sheet'!G63 -> 20963.93 | H11: ='Data Sheet'!H63 -> 10251.09 | I11: ='Data Sheet'!I63 -> 14274.5 | ... K11: ='Data Sheet'!K63 -> 65806
A12: Investments | B12: ='Data Sheet'!B64 -> 23767.02 | C12: ='Data Sheet'!C64 -> 20337.92 | D12: ='Data Sheet'!D64 -> 20812.75 | E12: ='Data Sheet'!E64 -> 15770.72 | F12: ='Data Sheet'!F64 -> 16308.48 | G12: ='Data Sheet'!G64 -> 24620.28 | H12: ='Data Sheet'!H64 -> 29379.53 | I12: ='Data Sheet'!I64 -> 26379.16 | ... K12: ='Data Sheet'!K64 -> 35656
A13: Other Assets | B13: ='Data Sheet'!B65 -> 106266.4 | C13: ='Data Sheet'!C65 -> 122599.52 | D13: ='Data Sheet'!D65 -> 144931.7 | E13: ='Data Sheet'!E65 -> 146814.46 | F13: ='Data Sheet'!F65 -> 141141.48 | G13: ='Data Sheet'!G65 -> 157278.09 | H13: ='Data Sheet'!H65 -> 150575.42 | I13: ='Data Sheet'!I65 -> 161941.01 | ... K13: ='Data Sheet'!K65 -> 159814
A14: Total | B14: ='Data Sheet'!B66 -> 263184.12 | C14: ='Data Sheet'!C66 -> 272580.36 | D14: ='Data Sheet'!D66 -> 327191.81 | E14: ='Data Sheet'!E66 -> 305703.49 | F14: ='Data Sheet'!F66 -> 320179.39 | G14: ='Data Sheet'!G66 -> 341569.91 | H14: ='Data Sheet'!H66 -> 329061.49 | I14: ='Data Sheet'!I66 -> 334674.43 | ... K14: ='Data Sheet'!K66 -> 376973
A16: Working Capital | B16: =B13-B7 -> -8605.35 | C16: =C13-C7 -> -13314.97 | D16: =D13-D7 -> 2118.27 | E16: =E13-E7 -> 7465.87 | F16: =F13-F7 -> 8828.26 | G16: =G13-G7 -> 13085.47 | H16: =H13-H7 -> 12524.2 | I16: =I13-I7 -> 6701.81 | ... K16: =K13-K7 -> -29475
A17: Debtors | B17: ='Data Sheet'!B67 -> 13570.91 | C17: ='Data Sheet'!C67 -> 14075.55 | D17: ='Data Sheet'!D67 -> 19893.3 | E17: ='Data Sheet'!E67 -> 18996.17 | F17: ='Data Sheet'!F67 -> 11172.69 | G17: ='Data Sheet'!G67 -> 12679.08 | H17: ='Data Sheet'!H67 -> 12442.12 | I17: ='Data Sheet'!I67 -> 15737.97 | ... K17: ='Data Sheet'!K67 -> 13248
A18: Inventory | B18: ='Data Sheet'!B68 -> 32655.73 | C18: ='Data Sheet'!C68 -> 35085.31 | D18: ='Data Sheet'!D68 -> 42137.63 | E18: ='Data Sheet'!E68 -> 39013.73 | F18: ='Data Sheet'!F68 -> 37456.88 | G18: ='Data Sheet'!G68 -> 36088.59 | H18: ='Data Sheet'!H68 -> 35240.34 | I18: ='Data Sheet'!I68 -> 40755.39 | ... K18: ='Data Sheet'!K68 -> 47269
A20: Debtor Days | B20: =IF('Profit & Loss'!B4>0,'Balance Sheet'!B17/('Profit & Loss'!B4/365),0) -> 18.141227 | C20: =IF('Profit & Loss'!C4>0,'Balance Sheet'!C17/('Profit & Loss'!C4/365),0) -> 19.049753 | D20: =IF('Profit & Loss'!D4>0,'Balance Sheet'!D17/('Profit & Loss'!D4/365),0) -> 24.904965 | E20: =IF('Profit & Loss'!E4>0,'Balance Sheet'!E17/('Profit & Loss'!E4/365),0) -> 22.963631 | F20: =IF('Profit & Loss'!F4>0,'Balance Sheet'!F17/('Profit & Loss'!F4/365),0) -> 15.620575 | G20: =IF('Profit & Loss'!G4>0,'Balance Sheet'!G17/('Profit & Loss'!G4/365),0) -> 18.526667 | H20: =IF('Profit & Loss'!H4>0,'Balance Sheet'!H17/('Profit & Loss'!H4/365),0) -> 16.309265 | I20: =IF('Profit & Loss'!I4>0,'Balance Sheet'!I17/('Profit & Loss'!I4/365),0) -> 16.603779 | ... K20: =IF('Profit & Loss'!K4>0,'Balance Sheet'!K17/('Profit & Loss'!K4/365),0) -> 10.997441
A21: Inventory Turnover | B21: =IF('Balance Sheet'!B18>0,'Profit & Loss'!B4/'Balance Sheet'!B18,0) -> 8.3613381 | C21: =IF('Balance Sheet'!C18>0,'Profit & Loss'!C4/'Balance Sheet'!C18,0) -> 7.6867643 | D21: =IF('Balance Sheet'!D18>0,'Profit & Loss'!D4/'Balance Sheet'!D18,0) -> 6.9190052 | E21: =IF('Balance Sheet'!E18>0,'Profit & Loss'!E4/'Balance Sheet'!E18,0) -> 7.7392856 | F21: =IF('Balance Sheet'!F18>0,'Profit & Loss'!F4/'Balance Sheet'!F18,0) -> 6.9698269 | G21: =IF('Balance Sheet'!G18>0,'Profit & Loss'!G4/'Balance Sheet'!G18,0) -> 6.9217099 | H21: =IF('Balance Sheet'!H18>0,'Profit & Loss'!H4/'Balance Sheet'!H18,0) -> 7.9015588 | I21: =IF('Balance Sheet'!I18>0,'Profit & Loss'!I4/'Balance Sheet'!I18,0) -> 8.4888642 | ... K21: =IF('Balance Sheet'!K18>0,'Profit & Loss'!K4/'Balance Sheet'!K18,0) -> 9.3019738
A23: Return on Equity | B23: =IF(SUM('Balance Sheet'!B4:B5)>0,'Profit & Loss'!B12/SUM('Balance Sheet'!B4:B5),"") -> 0.14666189 | C23: =IF(SUM('Balance Sheet'!C4:C5)>0,'Profit & Loss'!C12/SUM('Balance Sheet'!C4:C5),"") -> 0.12838645 | D23: =IF(SUM('Balance Sheet'!D4:D5)>0,'Profit & Loss'!D12/SUM('Balance Sheet'!D4:D5),"") -> 0.094195818 | E23: =IF(SUM('Balance Sheet'!E4:E5)>0,'Profit & Loss'!E12/SUM('Balance Sheet'!E4:E5),"") -> -0.47900367 | F23: =IF(SUM('Balance Sheet'!F4:F5)>0,'Profit & Loss'!F12/SUM('Balance Sheet'!F4:F5),"") -> -0.19136226 | G23: =IF(SUM('Balance Sheet'!G4:G5)>0,'Profit & Loss'!G12/SUM('Balance Sheet'!G4:G5),"") -> -0.24347853 | H23: =IF(SUM('Balance Sheet'!H4:H5)>0,'Profit & Loss'!H12/SUM('Balance Sheet'!H4:H5),"") -> -0.25675834 | I23: =IF(SUM('Balance Sheet'!I4:I5)>0,'Profit & Loss'!I12/SUM('Balance Sheet'!I4:I5),"") -> 0.053269961 | ... K23: =IF(SUM('Balance Sheet'!K4:K5)>0,'Profit & Loss'!K12/SUM('Balance Sheet'!K4:K5),"") -> 0.23961634
A24: Return on Capital Emp | C24: =IF((B4+B5+B6+C4+C5+C6)>0,('Profit & Loss'!C10+'Profit & Loss'!C9)*2/(B4+B5+B6+C4+C5+C6),"") -> 0.095114631 | D24: =IF((C4+C5+C6+D4+D5+D6)>0,('Profit & Loss'!D10+'Profit & Loss'!D9)*2/(C4+C5+C6+D4+D5+D6),"") -> 0.098658176 | E24: =IF((D4+D5+D6+E4+E5+E6)>0,('Profit & Loss'!E10+'Profit & Loss'!E9)*2/(D4+D5+D6+E4+E5+E6),"") -> -0.14605144 | F24: =IF((E4+E5+E6+F4+F5+F6)>0,('Profit & Loss'!F10+'Profit & Loss'!F9)*2/(E4+E5+E6+F4+F5+F6),"") -> -0.018839365 | G24: =IF((F4+F5+F6+G4+G5+G6)>0,('Profit & Loss'!G10+'Profit & Loss'!G9)*2/(F4+F5+F6+G4+G5+G6),"") -> -0.012340819 | H24: =IF((G4+G5+G6+H4+H5+H6)>0,('Profit & Loss'!H10+'Profit & Loss'!H9)*2/(G4+G5+G6+H4+H5+H6),"") -> 0.011887353 | I24: =IF((H4+H5+H6+I4+I5+I6)>0,('Profit & Loss'!I10+'Profit & Loss'!I9)*2/(H4+H5+H6+I4+I5+I6),"") -> 0.073529898 | J24: =IF((I4+I5+I6+J4+J5+J6)>0,('Profit & Loss'!J10+'Profit & Loss'!J9)*2/(I4+I5+I6+J4+J5+J6),"") -> 0.19039483 | K24: =IF((J4+J5+J6+K4+K5+K6)>0,('Profit & Loss'!K10+'Profit & Loss'!K9)*2/(J4+J5+J6+K4+K5+K6),"") -> 0.23026014

Sheet Cash Flow
A1: ='Balance Sheet'!A1 -> TATA MOTORS LTD | E1: =UPDATE | J1: SCREENER.IN
A3: Narration | B3: ='Data Sheet'!B81 -> 42460 | C3: ='Data Sheet'!C81 -> 42825 | D3: ='Data Sheet'!D81 -> 43190 | E3: ='Data Sheet'!E81 -> 43555 | F3: ='Data Sheet'!F81 -> 43921 | G3: ='Data Sheet'!G81 -> 44286 | H3: ='Data Sheet'!H81 -> 44651 | I3: ='Data Sheet'!I81 -> 45016 | ... K3: ='Data Sheet'!K81 -> 45747
A4: Cash from Operating Activity | B4: ='Data Sheet'!B82 -> 37899.54 | C4: ='Data Sheet'!C82 -> 30199.25 | D4: ='Data Sheet'!D82 -> 23857.42 | E4: ='Data Sheet'!E82 -> 18890.75 | F4: ='Data Sheet'!F82 -> 26632.94 | G4: ='Data Sheet'!G82 -> 29000.51 | H4: ='Data Sheet'!H82 -> 14282.83 | I4: ='Data Sheet'!I82 -> 35388.01 | ... K4: ='Data Sheet'!K82 -> 63102
A5: Cash from Investing Activity | B5: ='Data Sheet'!B83 -> -36693.9 | C5: ='Data Sheet'!C83 -> -39571.4 | D5: ='Data Sheet'!D83 -> -25139.14 | E5: ='Data Sheet'!E83 -> -20878.07 | F5: ='Data Sheet'!F83 -> -33114.55 | G5: ='Data Sheet'!G83 -> -25672.5 | H5: ='Data Sheet'!H83 -> -4443.66 | I5: ='Data Sheet'!I83 -> -15417.17 | ... K5: ='Data Sheet'!K83 -> -49982
A6: Cash from Financing Activity | B6: ='Data Sheet'!B84 -> -3795.12 | C6: ='Data Sheet'!C84 -> 6205.3 | D6: ='Data Sheet'!D84 -> 2011.71 | E6: ='Data Sheet'!E84 -> 8830.37 | F6: ='Data Sheet'!F84 -> 3389.61 | G6: ='Data Sheet'!G84 -> 9904.2 | H6: ='Data Sheet'!H84 -> -3380.17 | I6: ='Data Sheet'!I84 -> -26242.9 | ... K6: ='Data Sheet'!K84 -> -18786
A7: Net Cash Flow | B7: ='Data Sheet'!B85 -> -2589.48 | C7: ='Data Sheet'!C85 -> -3166.85 | D7: ='Data Sheet'!D85 -> 729.99 | E7: ='Data Sheet'!E85 -> 6843.05 | F7: ='Data Sheet'!F85 -> -3092 | G7: ='Data Sheet'!G85 -> 13232.21 | H7: ='Data Sheet'!H85 -> 6459 | I7: ='Data Sheet'!I85 -> -6272.06 | ... K7: ='Data Sheet'!K85 -> -5666

Sheet Customization
A1: How to use it?
A3: You can customize this workbook as you want.
B4: You can add custom formating, add conditional formating, add your own formulas… do ANYTHING.
B5: Please don't edit the "Data Sheet" only.
A7: After customization, you can upload this back on Screener.
B8: Upload on: | C8: https://www.screener.in/excel/
A10: Download your customized workbooks now onwards.
B11: Now whenever you will "Export to excel" from Screener, it will export your customized file.
A14: TESTING:
B15: This is a testing feature currently.
B16: You can report any formula errors on the worksheet at: support@screener.in

Sheet Data Sheet
A1: COMPANY NAME | B1: TATA MOTORS LTD | E1: =IF(B2<>B3, "A NEW VERSION OF THE WORKSHEET IS AVAILABLE", "")
A2: LATEST VERSION | B2: 2.1 | E2: PLEASE DO NOT MAKE ANY CHANGES TO THIS SHEET
A3: CURRENT VERSION | B3: 2.1
A5: META
A6: Number of shares | B6: =IF(B9>0, B9/B8, 0) -> 368.14616
A7: Face Value | B7: 2
A8: Current Price | B8: 688.5
A9: Market Capitalization | B9: 253468.63
A15: PROFIT & LOSS
A16: Report Date | B16: 42460 | C16: 42825 | D16: 43190 | E16: 43555 | F16: 43921 | G16: 44286 | H16: 44651 | I16: 45016 | J16: 45382 | K16: 45747
A17: Sales | B17: 273045.6 | C17: 269692.51 | D17: 291550.48 | E17: 301938.4 | F17: 261067.97 | G17: 249794.75 | H17: 278453.62 | I17: 345966.97 | J17: 434016 | K17: 439695
A18: Raw Material Cost | B18: 166134.01 | C18: 173294.08 | D18: 187896.58 | E18: 194267.91 | F18: 164899.82 | G18: 153607.36 | H18: 179295.33 | I18: 231251.26 | J18: 274321 | K18: 268950
A19: Change in Inventory | B19: 2750.99 | C19: 7399.92 | D19: 2046.58 | E19: -2053.28 | F19: -2231.19 | G19: -4684.16 | H19: -1590.49 | I19: 4781.62 | J19: 1566 | K19: -2836
A20: Power and Fuel | B20: 1143.63 | C20: 1159.82 | D20: 1308.08 | E20: 1585.93 | F20: 1264.95 | G20: 1112.87 | H20: 2178.29 | I20: 2513.33 | J20: 2189 | K20: 2443
A21: Other Mfr. Exp | B21: 12101.53 | C21: 10067.37 | D21: 10971.66 | E21: 11694.54 | F21: 11541.51 | G21: 8273.17 | H21: 9427.38 | I21: 11765.97 | J21: 17446 | K21: 18813
A22: Employee Cost | B22: 28880.89 | C22: 28332.89 | D22: 30300.09 | E22: 33243.87 | F22: 30438.6 | G22: 27648.48 | H22: 30808.52 | I22: 33654.7 | J22: 41990 | K22: 47767
A23: Selling and admin | B23: 21991.9 | C23: 30039.38 | D23: 31004.58 | E23: 32719.8 | F23: 29248.32 | G23: 23015.79 | H23: 29205.4 | I23: 34839.19 | J23: 42765 | K23: 47099
A24: Other Expenses | B24: 7149.38 | C24: 4610.2 | D24: 658.39 | E24: 1708.74 | F24: 3456.51 | G24: -834.51 | H24: 1228.12 | I24: 4908.34 | J24: -953 | K24: -3429
A25: Other Income | B25: -2669.62 | C25: 1869.1 | D25: 5932.73 | E25: -26686.25 | F25: 101.71 | G25: -11117.83 | H25: 2424.05 | I25: 6663.97 | J25: 4792 | K25: 11774
A26: Depreciation | B26: 16710.78 | C26: 17904.99 | D26: 21553.59 | E26: 23590.63 | F26: 21425.43 | G26: 23546.71 | H26: 24835.69 | I26: 24860.36 | J26: 27239 | K26: 23256
A27: Interest | B27: 4889.08 | C27: 4238.01 | D27: 4681.79 | E27: 5758.6 | F27: 7243.33 | G27: 8097.17 | H27: 9311.86 | I27: 10225.48 | J27: 7594 | K27: 5083
... A30: Net profit | B30: 11579.31 | C30: 7454.36 | D30: 8988.91 | E30: -28826.23 | F30: -12070.85 | G30: -13451.39 | H30: -11441.47 | I30: 2414.29 | J30: 31399 | K30: 27830
A31: Dividend Amount | B31: 67.92 | I31: 766.02 | J31: 2301 | K31: 2208
A40: Quarters
A41: Report Date | B41: 44926 | C41: 45016 | D41: 45107 | E41: 45199 | F41: 45291 | G41: 45382 | H41: 45473 | I41: 45565 | J41: 45657 | K41: 45747
A42: Sales | B42: 88488.59 | C42: 105932.35 | D42: 102236 | E42: 105129 | F42: 110577 | G42: 119033 | H42: 108048 | I42: 101450 | J42: 112608 | K42: 119503
A43: Expenses | B43: 77668.35 | C43: 92817.95 | D43: 89019 | E43: 91362 | F43: 95159 | G43: 102348 | H43: 92263 | I43: 89291 | J43: 100185 | K43: 102685
A44: Other Income | B44: 1129.98 | C44: 1452.86 | D44: 895 | E44: 1557 | F44: 1604 | G44: 1412 | H44: 1747 | I44: 1647 | J44: 1700 | K44: 1057
A45: Depreciation | B45: 6071.78 | C45: 7050.2 | D45: 6633 | E45: 6637 | F45: 6850 | G45: 7143 | H45: 6574 | I45: 6005 | J45: 5399 | K45: 5295
A46: Interest | B46: 2675.83 | C46: 2641.67 | D46: 2615 | E46: 2652 | F46: 2485 | G46: 1645 | H46: 2088 | I46: 2034 | J46: 1119 | K46: 1076
A47: Profit before tax | B47: 3202.61 | C47: 4875.39 | D47: 4864 | E47: 6035 | F47: 7687 | G47: 9309 | H47: 8870 | I47: 5767 | J47: 7605 | K47: 11504
A48: Tax | B48: 262.83 | C48: -620.65 | D48: 1563 | E48: 2203 | F48: 542 | G48: -8219 | H48: 3178 | I48: 2317 | J48: 2120 | K48: 2948
A49: Net profit | B49: 2957.71 | C49: 5407.79 | D49: 3203 | E49: 3764 | F49: 7025 | G49: 17407 | H49: 5566 | I49: 3343 | J49: 5406 | K49: 8470
A50: Operating Profit | B50: 10820.24 | C50: 13114.4 | D50: 13217 | E50: 13767 | F50: 15418 | G50: 16685 | H50: 15785 | I50: 12159 | J50: 12423 | K50: 16818
A55: BALANCE SHEET
A56: Report Date | B56: 42460 | C56: 42825 | D56: 43190 | E56: 43555 | F56: 43921 | G56: 44286 | H56: 44651 | I56: 45016 | J56: 45382 | K56: 45747
A57: Equity Share Capital | B57: 679.18 | C57: 679.22 | D57: 679.22 | E57: 679.22 | F57: 719.54 | G57: 765.81 | H57: 765.88 | I57: 766.02 | J57: 767 | K57: 736
A58: Reserves | B58: 78273.23 | C58: 57382.67 | D58: 94748.69 | E58: 59500.34 | F58: 62358.99 | G58: 54480.91 | H58: 43795.36 | I58: 44555.77 | J58: 84151 | K58: 115408
A59: Borrowings | B59: 69359.96 | C59: 78603.98 | D59: 88950.47 | E59: 106175.34 | F59: 124787.64 | G59: 142130.57 | H59: 146449.03 | I59: 134113.44 | J59: 107264 | K59: 71540
A60: Other Liabilities | B60: 114871.75 | C60: 135914.49 | D60: 142813.43 | E60: 139348.59 | F60: 132313.22 | G60: 144192.62 | H60: 138051.22 | I60: 155239.2 | J60: 177339 | K60: 189289
A61: Total | B61: 263184.12 | C61: 272580.36 | D61: 327191.81 | E61: 305703.49 | F61: 320179.39 | G61: 341569.91 | H61: 329061.49 | I61: 334674.43 | J61: 369521 | K61: 376973
A62: Net Block | B62: 107231.76 | C62: 95944.08 | D62: 121413.86 | E62: 111234.47 | F62: 127107.14 | G62: 138707.61 | H62: 138855.45 | I62: 132079.76 | J62: 121285 | K62: 115697
A63: Capital Work in Progress | B63: 25918.94 | C63: 33698.84 | D63: 40033.5 | E63: 31883.84 | F63: 35622.29 | G63: 20963.93 | H63: 10251.09 | I63: 14274.5 | J63: 35698 | K63: 65806
A64: Investments | B64: 23767.02 | C64: 20337.92 | D64: 20812.75 | E64: 15770.72 | F64: 16308.48 | G64: 24620.28 | H64: 29379.53 | I64: 26379.16 | J64: 22971 | K64: 35656
A65: Other Assets | B65: 106266.4 | C65: 122599.52 | D65: 144931.7 | E65: 146814.46 | F65: 141141.48 | G65: 157278.09 | H65: 150575.42 | I65: 161941.01 | J65: 189567 | K65: 159814
A66: Total | B66: 263184.12 | C66: 272580.36 | D66: 327191.81 | E66: 305703.49 | F66: 320179.39 | G66: 341569.91 | H66: 329061.49 | I66: 334674.43 | J66: 369521 | K66: 376973
A67: Receivables | B67: 13570.91 | C67: 14075.55 | D67: 19893.3 | E67: 18996.17 | F67: 11172.69 | G67: 12679.08 | H67: 12442.12 | I67: 15737.97 | J67: 16952 | K67: 13248
... A70: No. of Equity Shares | B70: 3395930306 | C70: 3396100719 | D70: 3396100719 | E70: 3396100719 | F70: 3597726185 | G70: 3829060661 | H70: 3829414903 | I70: 3830097221 | J70: 3832491897 | K70: 3681348742
A71: New Bonus Shares
A72: Face value | B72: 2 | C72: 2 | D72: 2 | E72: 2 | F72: 2 | G72: 2 | H72: 2 | I72: 2 | J72: 2 | K72: 2
A80: CASH FLOW:
A81: Report Date | B81: 42460 | C81: 42825 | D81: 43190 | E81: 43555 | F81: 43921 | G81: 44286 | H81: 44651 | I81: 45016 | J81: 45382 | K81: 45747
A82: Cash from Operating Activity | B82: 37899.54 | C82: 30199.25 | D82: 23857.42 | E82: 18890.75 | F82: 26632.94 | G82: 29000.51 | H82: 14282.83 | I82: 35388.01 | J82: 67915 | K82: 63102
A83: Cash from Investing Activity | B83: -36693.9 | C83: -39571.4 | D83: -25139.14 | E83: -20878.07 | F83: -33114.55 | G83: -25672.5 | H83: -4443.66 | I83: -15417.17 | J83: -22781 | K83: -49982
A84: Cash from Financing Activity | B84: -3795.12 | C84: 6205.3 | D84: 2011.71 | E84: 8830.37 | F84: 3389.61 | G84: 9904.2 | H84: -3380.17 | I84: -26242.9 | J84: -37006 | K84: -18786
A85: Net Cash Flow | B85: -2589.48 | C85: -3166.85 | D85: 729.99 | E85: 6843.05 | F85: -3092 | G85: 13232.21 | H85: 6459 | I85: -6272.06 | J85: 8128 | K85: -5666
A90: PRICE: | B90: 386.6 | C90: 465.85 | D90: 326.85 | E90: 174.25 | F90: 71.05 | G90: 301.8 | H90: 433.75 | I90: 420.8 | J90: 992.8 | K90: 674.45
A92: DERIVED:
A93: Adjusted Equity Shares in Cr | B93: 288.72 | C93: 288.73 | D93: 288.73 | E93: 288.73 | F93: 308.9 | G93: 332.03 | H93: 332.07 | I93: 332.13 | J93: 332.37 | K93: 368.13
